Workbook
Name Slicer_Color_B_W: #N/A
Name Slicer_Country: #N/A
Name Slicer_Genre: #N/A
Name Slicer_Recommended_Movie: #N/A
Name Slicer_Release_Year: #N/A

Sheet imdb
A1: Title | B1: Release Date | C1: Color/B&W | D1: Genre | E1: Language | F1: Country | G1: Rating | H1: Lead Actor | I1: Director Name | J1: Lead Actor FB Likes | K1: Cast FB Likes | L1: Director FB Likes | M1: Movie FB Likes | N1: IMDb Score (1-10) | O1: Total Reviews | P1: Duration (min) | Q1: Gross Revenue | R1: Budget | S1: Profit | T1: ROI(%) | U1: Success Score | V1: Release Year | W1: Release Month | X1: Director Name(Clean) | Y1: Movie Title(UPPER) | Z1: Performance Status | AA1: Genre Category | AB1: Recommended Movie | AC1: Audience Buzz Mismatch
A2: Avatar | B2: 39950 | C2: Color | D2: Action | E2: English | F2: USA | G2: PG-13 | H2: CCH Pounder | I2: James Cameron | J2: 1000 | K2: 4834 | L2: 0 | M2: 33000 | N2: 7.9 | O2: 723 | P2: 178 | Q2: 760505847 | R2: 237000000 | S2: =Q2-R2 -> 523505847 | T2: =IF(R2>0, (Q2-R2)/R2, 0) -> 2.2088854 | U2: =(N2*4) + (T2*0.4) + (M2/10000) -> 35.783554 | V2: =YEAR(B2) -> 2009 | W2: =TEXT(B2, "mmmm") -> may | X2: =TRIM(I2) -> James Cameron | Y2: =UPPER(A2) -> AVATAR | Z2: =IF(AND(R2>50000000, S2<0), "Underperformer", IF(AND(R2<10000000, S2>50000000), "Overperformer", "Normal")) -> Normal | AA2: =VLOOKUP(D2, lookups!$A$2:$B$18, 2, FALSE) -> High Budget | AB2: =IF(AND(N2>7, T2>1, U2>70), "Recommended", "Not Recommended") -> Not Recommended | AC2: =IF(N2>=8, "High Buzz / High Score", IF(AND(N2<6, T2<1), "High Buzz Mismatch", "Normal")) -> Normal
A3: Titanic | B3: 35500 | C3: Color | D3: Drama | E3: English | F3: USA | G3: PG-13 | H3: Leonardo DiCaprio | I3: James Cameron | J3: 29000 | K3: 45223 | L3: 0 | M3: 26000 | N3: 7.7 | O3: 315 | P3: 194 | Q3: 658672302 | R3: 200000000 | S3: =Q3-R3 -> 458672302 | T3: =IF(R3>0, (Q3-R3)/R3, 0) -> 2.2933615 | U3: =(N3*4) + (T3*0.4) + (M3/10000) -> 34.317345 | V3: =YEAR(B3) -> 1997 | W3: =TEXT(B3, "mmmm") -> mart | X3: =TRIM(I3) -> James Cameron | Y3: =UPPER(A3) -> TİTANİC | Z3: =IF(AND(R3>50000000, S3<0), "Underperformer", IF(AND(R3<10000000, S3>50000000), "Overperformer", "Normal")) -> Normal | AA3: =VLOOKUP(D3, lookups!$A$2:$B$18, 2, FALSE) -> Medium Budget | AB3: =IF(AND(N3>7, T3>1, U3>70), "Recommended", "Not Recommended") -> Not Recommended | AC3: =IF(N3>=8, "High Buzz / High Score", IF(AND(N3<6, T3<1), "High Buzz Mismatch", "Normal")) -> Normal
A4: Jurassic World | B4: 42188 | C4: Color | D4: Action | E4: English | F4: USA | G4: PG-13 | H4: Bryce Dallas Howard | I4: Colin Trevorrow | J4: 3000 | K4: 8458 | L4: 365 | M4: 150000 | N4: 7 | O4: 644 | P4: 124 | Q4: 652177271 | R4: 150000000 | S4: =Q4-R4 -> 502177271 | T4: =IF(R4>0, (Q4-R4)/R4, 0) -> 3.3478485 | U4: =(N4*4) + (T4*0.4) + (M4/10000) -> 44.339139 | V4: =YEAR(B4) -> 2015 | W4: =TEXT(B4, "mmmm") -> iyul | X4: =TRIM(I4) -> Colin Trevorrow | Y4: =UPPER(A4) -> JURASSİC WORLD | Z4: =IF(AND(R4>50000000, S4<0), "Underperformer", IF(AND(R4<10000000, S4>50000000), "Overperformer", "Normal")) -> Normal | AA4: =VLOOKUP(D4, lookups!$A$2:$B$18, 2, FALSE) -> High Budget | AB4: =IF(AND(N4>7, T4>1, U4>70), "Recommended", "Not Recommended") -> Not Recommended | AC4: =IF(N4>=8, "High Buzz / High Score", IF(AND(N4<6, T4<1), "High Buzz Mismatch", "Normal")) -> Normal
A5: The Avengers | B5: 41118 | C5: Color | D5: Action | E5: English | F5: USA | G5: PG-13 | H5: Chris Hemsworth | I5: Joss Whedon | J5: 26000 | K5: 87697 | L5: 0 | M5: 123000 | N5: 8.1 | O5: 703 | P5: 173 | Q5: 623279547 | R5: 220000000 | S5: =Q5-R5 -> 403279547 | T5: =IF(R5>0, (Q5-R5)/R5, 0) -> 1.8330888 | U5: =(N5*4) + (T5*0.4) + (M5/10000) -> 45.433236 | V5: =YEAR(B5) -> 2012 | W5: =TEXT(B5, "mmmm") -> iyul | X5: =TRIM(I5) -> Joss Whedon | Y5: =UPPER(A5) -> THE AVENGERS | Z5: =IF(AND(R5>50000000, S5<0), "Underperformer", IF(AND(R5<10000000, S5>50000000), "Overperformer", "Normal")) -> Normal | AA5: =VLOOKUP(D5, lookups!$A$2:$B$18, 2, FALSE) -> High Budget | AB5: =IF(AND(N5>7, T5>1, U5>70), "Recommended", "Not Recommended") -> Not Recommended | AC5: =IF(N5>=8, "High Buzz / High Score", IF(AND(N5<6, T5<1), "High Buzz Mismatch", "Normal")) -> High Buzz / High Score
A6: The Dark Knight | B6: 39577 | C6: Color | D6: Action | E6: English | F6: USA | G6: PG-13 | H6: Christian Bale | I6: Christopher Nolan | J6: 23000 | K6: 57802 | L6: 22000 | M6: 37000 | N6: 9 | O6: 645 | P6: 152 | Q6: 533316061 | R6: 185000000 | S6: =Q6-R6 -> 348316061 | T6: =IF(R6>0, (Q6-R6)/R6, 0) -> 1.8827895 | U6: =(N6*4) + (T6*0.4) + (M6/10000) -> 40.453116 | V6: =YEAR(B6) -> 2008 | W6: =TEXT(B6, "mmmm") -> may | X6: =TRIM(I6) -> Christopher Nolan | Y6: =UPPER(A6) -> THE DARK KNİGHT | Z6: =IF(AND(R6>50000000, S6<0), "Underperformer", IF(AND(R6<10000000, S6>50000000), "Overperformer", "Normal")) -> Normal | AA6: =VLOOKUP(D6, lookups!$A$2:$B$18, 2, FALSE) -> High Budget | AB6: =IF(AND(N6>7, T6>1, U6>70), "Recommended", "Not Recommended") -> Not Recommended | AC6: =IF(N6>=8, "High Buzz / High Score", IF(AND(N6<6, T6<1), "High Buzz Mismatch", "Normal")) -> High Buzz / High Score
A7: Star Wars: Episode I - The Phantom Menace | B7: 36330 | C7: Color | D7: Action | E7: English | F7: USA | G7: PG | H7: Natalie Portman | I7: George Lucas | J7: 20000 | K7: 37723 | L7: 0 | M7: 13000 | N7: 6.5 | O7: 320 | P7: 136 | Q7: 474544677 | R7: 115000000 | S7: =Q7-R7 -> 359544677 | T7: =IF(R7>0, (Q7-R7)/R7, 0) -> 3.1264755 | U7: =(N7*4) + (T7*0.4) + (M7/10000) -> 28.55059 | V7: =YEAR(B7) -> 1999 | W7: =TEXT(B7, "mmmm") -> iyun | X7: =TRIM(I7) -> George Lucas | Y7: =UPPER(A7) -> STAR WARS: EPİSODE I - THE PHANTOM MENACE | Z7: =IF(AND(R7>50000000, S7<0), "Underperformer", IF(AND(R7<10000000, S7>50000000), "Overperformer", "Normal")) -> Normal | AA7: =VLOOKUP(D7, lookups!$A$2:$B$18, 2, FALSE) -> High Budget | AB7: =IF(AND(N7>7, T7>1, U7>70), "Recommended", "Not Recommended") -> Not Recommended | AC7: =IF(N7>=8, "High Buzz / High Score", IF(AND(N7<6, T7<1), "High Buzz Mismatch", "Normal")) -> Normal
A8: Star Wars: Episode IV - A New Hope | B8: 28163 | C8: Color | D8: Action | E8: English | F8: USA | G8: PG | H8: Harrison Ford | I8: George Lucas | J8: 11000 | K8: 13485 | L8: 0 | M8: 33000 | N8: 8.7 | O8: 282 | P8: 125 | Q8: 460935665 | R8: 11000000 | S8: =Q8-R8 -> 449935665 | T8: =IF(R8>0, (Q8-R8)/R8, 0) -> 40.903242 | U8: =(N8*4) + (T8*0.4) + (M8/10000) -> 54.461297 | V8: =YEAR(B8) -> 1977 | W8: =TEXT(B8, "mmmm") -> fevral | X8: =TRIM(I8) -> George Lucas | Y8: =UPPER(A8) -> STAR WARS: EPİSODE IV - A NEW HOPE | Z8: =IF(AND(R8>50000000, S8<0), "Underperformer", IF(AND(R8<10000000, S8>50000000), "Overperformer", "Normal")) -> Normal | AA8: =VLOOKUP(D8, lookups!$A$2:$B$18, 2, FALSE) -> High Budget | AB8: =IF(AND(N8>7, T8>1, U8>70), "Recommended", "Not Recommended") -> Not Recommended | AC8: =IF(N8>=8, "High Buzz / High Score", IF(AND(N8<6, T8<1), "High Buzz Mismatch", "Normal")) -> High Buzz / High Score
A9: Avengers: Age of Ultron | B9: 42055 | C9: Color | D9: Action | E9: English | F9: USA | G9: PG-13 | H9: Chris Hemsworth | I9: Joss Whedon | J9: 26000 | K9: 92000 | L9: 0 | M9: 118000 | N9: 7.5 | O9: 635 | P9: 141 | Q9: 458991599 | R9: 250000000 | S9: =Q9-R9 -> 208991599 | T9: =IF(R9>0, (Q9-R9)/R9, 0) -> 0.8359664 | U9: =(N9*4) + (T9*0.4) + (M9/10000) -> 42.134387 | V9: =YEAR(B9) -> 2015 | W9: =TEXT(B9, "mmmm") -> fevral | X9: =TRIM(I9) -> Joss Whedon | Y9: =UPPER(A9) -> AVENGERS: AGE OF ULTRON | Z9: =IF(AND(R9>50000000, S9<0), "Underperformer", IF(AND(R9<10000000, S9>50000000), "Overperformer", "Normal")) -> Normal | AA9: =VLOOKUP(D9, lookups!$A$2:$B$18, 2, FALSE) -> High Budget | AB9: =IF(AND(N9>7, T9>1, U9>70), "Recommended", "Not Recommended") -> Not Recommended | AC9: =IF(N9>=8, "High Buzz / High Score", IF(AND(N9<6, T9<1), "High Buzz Mismatch", "Normal")) -> Normal
A10: The Dark Knight Rises | B10: 41108 | C10: Color | D10: Action | E10: English | F10: USA | G10: PG-13 | H10: Tom Hardy | I10: Christopher Nolan | J10: 27000 | K10: 106759 | L10: 22000 | M10: 164000 | N10: 8.4 | O10: 813 | P10: 164 | Q10: 448130642 | R10: 250000000 | S10: =Q10-R10 -> 198130642 | T10: =IF(R10>0, (Q10-R10)/R10, 0) -> 0.79252257 | U10: =(N10*4) + (T10*0.4) + (M10/10000) -> 50.317009 | V10: =YEAR(B10) -> 2012 | W10: =TEXT(B10, "mmmm") -> iyul | X10: =TRIM(I10) -> Christopher Nolan | Y10: =UPPER(A10) -> THE DARK KNİGHT RİSES | Z10: =IF(AND(R10>50000000, S10<0), "Underperformer", IF(AND(R10<10000000, S10>50000000), "Overperformer", "Normal")) -> Normal | AA10: =VLOOKUP(D10, lookups!$A$2:$B$18, 2, FALSE) -> High Budget | AB10: =IF(AND(N10>7, T10>1, U10>70), "Recommended", "Not Recommended") -> Not Recommended | AC10: =IF(N10>=8, "High Buzz / High Score", IF(AND(N10<6, T10<1), "High Buzz Mismatch", "Normal")) -> High Buzz / High Score
A11: Shrek 2 | B11: 38076 | C11: Color | D11: Adventure | E11: English | F11: USA | G11: PG | H11: Rupert Everett | I11: Andrew Adamson | J11: 692 | K11: 1148 | L11: 80 | M11: 0 | N11: 7.2 | O11: 205 | P11: 93 | Q11: 436471036 | R11: 150000000 | S11: =Q11-R11 -> 286471036 | T11: =IF(R11>0, (Q11-R11)/R11, 0) -> 1.9098069 | U11: =(N11*4) + (T11*0.4) + (M11/10000) -> 29.563923 | V11: =YEAR(B11) -> 2004 | W11: =TEXT(B11, "mmmm") -> mart | X11: =TRIM(I11) -> Andrew Adamson | Y11: =UPPER(A11) -> SHREK 2 | Z11: =IF(AND(R11>50000000, S11<0), "Underperformer", IF(AND(R11<10000000, S11>50000000), "Overperformer", "Normal")) -> Normal | AA11: =VLOOKUP(D11, lookups!$A$2:$B$18, 2, FALSE) -> High Budget | AB11: =IF(AND(N11>7, T11>1, U11>70), "Recommended", "Not Recommended") -> Not Recommended | AC11: =IF(N11>=8, "High Buzz / High Score", IF(AND(N11<6, T11<1), "High Buzz Mismatch", "Normal")) -> Normal
A12: Indiana Jones and the Kingdom of the Crystal Skull | B12: 39808 | C12: Color | D12: Action | E12: English | F12: USA | G12: PG-13 | H12: Harrison Ford | I12: Steven Spielberg | J12: 11000 | K12: 14959 | L12: 14000 | M12: 5000 | N12: 6.2 | O12: 470 | P12: 122 | Q12: 317011114 | R12: 185000000 | S12: =Q12-R12 -> 132011114 | T12: =IF(R12>0, (Q12-R12)/R12, 0) -> 0.71357359 | U12: =(N12*4) + (T12*0.4) + (M12/10000) -> 25.585429 | V12: =YEAR(B12) -> 2008 | W12: =TEXT(B12, "mmmm") -> dekabr | X12: =TRIM(I12) -> Steven Spielberg | Y12: =UPPER(A12) -> INDİANA JONES AND THE KİNGDOM OF THE CRYSTAL SKULL | Z12: =IF(AND(R12>50000000, S12<0), "Underperformer", IF(AND(R12<10000000, S12>50000000), "Overperformer", "Normal")) -> Normal | AA12: =VLOOKUP(D12, lookups!$A$2:$B$18, 2, FALSE) -> High Budget | AB12: =IF(AND(N12>7, T12>1, U12>70), "Recommended", "Not Recommended") -> Not Recommended | AC12: =IF(N12>=8, "High Buzz / High Score", IF(AND(N12<6, T12<1), "High Buzz Mismatch", "Normal")) -> Normal
A13: The Hunger Games: Catching Fire | B13: 41347 | C13: Color | D13: Adventure | E13: English | F13: USA | G13: PG-13 | H13: Jennifer Lawrence | I13: Francis Lawrence | J13: 34000 | K13: 49355 | L13: 508 | M13: 82000 | N13: 7.6 | O13: 502 | P13: 146 | Q13: 424645577 | R13: 130000000 | S13: =Q13-R13 -> 294645577 | T13: =IF(R13>0, (Q13-R13)/R13, 0) -> 2.2665044 | U13: =(N13*4) + (T13*0.4) + (M13/10000) -> 39.506602 | V13: =YEAR(B13) -> 2013 | W13: =TEXT(B13, "mmmm") -> mart | X13: =TRIM(I13) -> Francis Lawrence | Y13: =UPPER(A13) -> THE HUNGER GAMES: CATCHİNG FİRE | Z13: =IF(AND(R13>50000000, S13<0), "Underperformer", IF(AND(R13<10000000, S13>50000000), "Overperformer", "Normal")) -> Normal | AA13: =VLOOKUP(D13, lookups!$A$2:$B$18, 2, FALSE) -> High Budget | AB13: =IF(AND(N13>7, T13>1, U13>70), "Recommended", "Not Recommended") -> Not Recommended | AC13: =IF(N13>=8, "High Buzz / High Score", IF(AND(N13<6, T13<1), "High Buzz Mismatch", "Normal")) -> Normal
... A2732: Promised Land | B2732: 41253 | C2732: Color | D2732: Drama | E2732: English | F2732: USA | G2732: R | H2732: Matt Damon | I2732: Gus Van Sant | J2732: 13000 | K2732: 14544 | L2732: 835 | M2732: 10000 | N2732: 6.6 | O2732: 242 | P2732: 106 | Q2732: 7556708 | R2732: 15000000 | S2732: =Q2732-R2732 -> -7443292 | T2732: =IF(R2732>0, (Q2732-R2732)/R2732, 0) -> -0.49621947 | U2732: =(N2732*4) + (T2732*0.4) + (M2732/10000) -> 27.201512 | V2732: =YEAR(B2732) -> 2012 | W2732: =TEXT(B2732, "mmmm") -> dekabr | X2732: =TRIM(I2732) -> Gus Van Sant | Y2732: =UPPER(A2732) -> PROMİSED LAND | Z2732: =IF(AND(R2732>50000000, S2732<0), "Underperformer", IF(AND(R2732<10000000, S2732>50000000), "Overperformer", "Normal")) -> Normal | AA2732: =VLOOKUP(D2732, lookups!$A$2:$B$18, 2, FALSE) -> Medium Budget | AB2732: =IF(AND(N2732>7, T2732>1, U2732>70), "Recommended", "Not Recommended") -> Not Recommended | AC2732: =IF(N2732>=8, "High Buzz / High Score", IF(AND(N2732<6, T2732<1), "High Buzz Mismatch", "Normal")) -> Normal
A2733: Dolphins and Whales 3D: Tribes of the Ocean | B2733: 39622 | C2733: Color | D2733: Adventure | E2733: English | F2733: UK | H2733: Charlotte Rampling | I2733: Jean-Jacques Mantello | J2733: 844 | K2733: 844 | L2733: 0 | M2733: 28 | N2733: 6.5 | O2733: 9 | P2733: 42 | Q2733: 7518876 | R2733: 6000000 | S2733: =Q2733-R2733 -> 1518876 | T2733: =IF(R2733>0, (Q2733-R2733)/R2733, 0) -> 0.253146 | U2733: =(N2733*4) + (T2733*0.4) + (M2733/10000) -> 26.104058 | V2733: =YEAR(B2733) -> 2008 | W2733: =TEXT(B2733, "mmmm") -> iyun | X2733: =TRIM(I2733) -> Jean-Jacques Mantello | Y2733: =UPPER(A2733) -> DOLPHİNS AND WHALES 3D: TRİBES OF THE OCEAN | Z2733: =IF(AND(R2733>50000000, S2733<0), "Underperformer", IF(AND(R2733<10000000, S2733>50000000), "Overperformer", "Normal")) -> Normal | AA2733: =VLOOKUP(D2733, lookups!$A$2:$B$18, 2, FALSE) -> High Budget | AB2733: =IF(AND(N2733>7, T2733>1, U2733>70), "Recommended", "Not Recommended") -> Not Recommended | AC2733: =IF(N2733>=8, "High Buzz / High Score", IF(AND(N2733<6, T2733<1), "High Buzz Mismatch", "Normal")) -> Normal
A2734: The Curse of the Jade Scorpion | B2734: 36991 | C2734: Color | D2734: Comedy | E2734: English | F2734: USA | G2734: PG-13 | H2734: Woody Allen | I2734: Woody Allen | J2734: 11000 | K2734: 12534 | L2734: 11000 | M2734: 826 | N2734: 6.8 | O2734: 116 | P2734: 103 | Q2734: 7496522 | R2734: 26000000 | S2734: =Q2734-R2734 -> -18503478 | T2734: =IF(R2734>0, (Q2734-R2734)/R2734, 0) -> -0.71167223 | U2734: =(N2734*4) + (T2734*0.4) + (M2734/10000) -> 26.997931 | V2734: =YEAR(B2734) -> 2001 | W2734: =TEXT(B2734, "mmmm") -> aprel | X2734: =TRIM(I2734) -> Woody Allen | Y2734: =UPPER(A2734) -> THE CURSE OF THE JADE SCORPİON | Z2734: =IF(AND(R2734>50000000, S2734<0), "Underperformer", IF(AND(R2734<10000000, S2734>50000000), "Overperformer", "Normal")) -> Normal | AA2734: =VLOOKUP(D2734, lookups!$A$2:$B$18, 2, FALSE) -> Medium Budget | AB2734: =IF(AND(N2734>7, T2734>1, U2734>70), "Recommended", "Not Recommended") -> Not Recommended | AC2734: =IF(N2734>=8, "High Buzz / High Score", IF(AND(N2734<6, T2734<1), "High Buzz Mismatch", "Normal")) -> Normal
A2735: Martian Child | B2735: 39311 | C2735: Color | D2735: Comedy | E2735: English | F2735: USA | G2735: PG | H2735: Oliver Platt | I2735: Menno Meyjes | J2735: 1000 | K2735: 2495 | L2735: 43 | M2735: 0 | N2735: 6.8 | O2735: 118 | P2735: 106 | Q2735: 7486906 | R2735: 27000000 | S2735: =Q2735-R2735 -> -19513094 | T2735: =IF(R2735>0, (Q2735-R2735)/R2735, 0) -> -0.72270719 | U2735: =(N2735*4) + (T2735*0.4) + (M2735/10000) -> 26.910917 | V2735: =YEAR(B2735) -> 2007 | W2735: =TEXT(B2735, "mmmm") -> avgust | X2735: =TRIM(I2735) -> Menno Meyjes | Y2735: =UPPER(A2735) -> MARTİAN CHİLD | Z2735: =IF(AND(R2735>50000000, S2735<0), "Underperformer", IF(AND(R2735<10000000, S2735>50000000), "Overperformer", "Normal")) -> Normal | AA2735: =VLOOKUP(D2735, lookups!$A$2:$B$18, 2, FALSE) -> Medium Budget | AB2735: =IF(AND(N2735>7, T2735>1, U2735>70), "Recommended", "Not Recommended") -> Not Recommended | AC2735: =IF(N2735>=8, "High Buzz / High Score", IF(AND(N2735<6, T2735<1), "High Buzz Mismatch", "Normal")) -> Normal
A2736: A Good Year | B2736: 38756 | C2736: Color | D2736: Comedy | E2736: English | F2736: USA | G2736: PG-13 | H2736: Archie Panjabi | I2736: Ridley Scott | J2736: 883 | K2736: 3611 | L2736: 0 | M2736: 9000 | N2736: 6.9 | O2736: 147 | P2736: 117 | Q2736: 7458269 | R2736: 35000000 | S2736: =Q2736-R2736 -> -27541731 | T2736: =IF(R2736>0, (Q2736-R2736)/R2736, 0) -> -0.7869066 | U2736: =(N2736*4) + (T2736*0.4) + (M2736/10000) -> 28.185237 | V2736: =YEAR(B2736) -> 2006 | W2736: =TEXT(B2736, "mmmm") -> fevral | X2736: =TRIM(I2736) -> Ridley Scott | Y2736: =UPPER(A2736) -> A GOOD YEAR | Z2736: =IF(AND(R2736>50000000, S2736<0), "Underperformer", IF(AND(R2736<10000000, S2736>50000000), "Overperformer", "Normal")) -> Normal | AA2736: =VLOOKUP(D2736, lookups!$A$2:$B$18, 2, FALSE) -> Medium Budget | AB2736: =IF(AND(N2736>7, T2736>1, U2736>70), "Recommended", "Not Recommended") -> Not Recommended | AC2736: =IF(N2736>=8, "High Buzz / High Score", IF(AND(N2736<6, T2736<1), "High Buzz Mismatch", "Normal")) -> Normal
A2737: Cyrus | B2737: 40389 | C2737: Color | D2737: Comedy | E2737: English | F2737: USA | G2737: R | H2737: Matt Walsh | I2737: Jay Duplass | J2737: 490 | K2737: 1136 | L2737: 157 | M2737: 0 | N2737: 6.3 | O2737: 223 | P2737: 91 | Q2737: 7455447 | R2737: 7000000 | S2737: =Q2737-R2737 -> 455447 | T2737: =IF(R2737>0, (Q2737-R2737)/R2737, 0) -> 0.065063857 | U2737: =(N2737*4) + (T2737*0.4) + (M2737/10000) -> 25.226026 | V2737: =YEAR(B2737) -> 2010 | W2737: =TEXT(B2737, "mmmm") -> iyul | X2737: =TRIM(I2737) -> Jay Duplass | Y2737: =UPPER(A2737) -> CYRUS | Z2737: =IF(AND(R2737>50000000, S2737<0), "Underperformer", IF(AND(R2737<10000000, S2737>50000000), "Overperformer", "Normal")) -> Normal | AA2737: =VLOOKUP(D2737, lookups!$A$2:$B$18, 2, FALSE) -> Medium Budget | AB2737: =IF(AND(N2737>7, T2737>1, U2737>70), "Recommended", "Not Recommended") -> Not Recommended | AC2737: =IF(N2737>=8, "High Buzz / High Score", IF(AND(N2737<6, T2737<1), "High Buzz Mismatch", "Normal")) -> Normal
A2738: Taking Woodstock | B2738: 40127 | C2738: Color | D2738: Comedy | E2738: English | F2738: USA | G2738: R | H2738: Imelda Staunton | I2738: Ang Lee | J2738: 579 | K2738: 1500 | L2738: 0 | M2738: 0 | N2738: 6.7 | O2738: 210 | P2738: 120 | Q2738: 7443007 | R2738: 30000000 | S2738: =Q2738-R2738 -> -22556993 | T2738: =IF(R2738>0, (Q2738-R2738)/R2738, 0) -> -0.75189977 | U2738: =(N2738*4) + (T2738*0.4) + (M2738/10000) -> 26.49924 | V2738: =YEAR(B2738) -> 2009 | W2738: =TEXT(B2738, "mmmm") -> noyabr | X2738: =TRIM(I2738) -> Ang Lee | Y2738: =UPPER(A2738) -> TAKİNG WOODSTOCK | Z2738: =IF(AND(R2738>50000000, S2738<0), "Underperformer", IF(AND(R2738<10000000, S2738>50000000), "Overperformer", "Normal")) -> Normal | AA2738: =VLOOKUP(D2738, lookups!$A$2:$B$18, 2, FALSE) -> Medium Budget | AB2738: =IF(AND(N2738>7, T2738>1, U2738>70), "Recommended", "Not Recommended") -> Not Recommended | AC2738: =IF(N2738>=8, "High Buzz / High Score", IF(AND(N2738<6, T2738<1), "High Buzz Mismatch", "Normal")) -> Normal
A2739: Harley Davidson and the Marlboro Man | B2739: 33494 | C2739: Color | D2739: Action | E2739: English | F2739: USA | G2739: R | H2739: Vanessa Williams | I2739: Simon Wincer | J2739: 1000 | K2739: 3671 | L2739: 23 | M2739: 0 | N2739: 6 | O2739: 30 | P2739: 98 | Q2739: 7434726 | R2739: 23000000 | S2739: =Q2739-R2739 -> -15565274 | T2739: =IF(R2739>0, (Q2739-R2739)/R2739, 0) -> -0.67675104 | U2739: =(N2739*4) + (T2739*0.4) + (M2739/10000) -> 23.7293 | V2739: =YEAR(B2739) -> 1991 | W2739: =TEXT(B2739, "mmmm") -> sentyabr | X2739: =TRIM(I2739) -> Simon Wincer | Y2739: =UPPER(A2739) -> HARLEY DAVİDSON AND THE MARLBORO MAN | Z2739: =IF(AND(R2739>50000000, S2739<0), "Underperformer", IF(AND(R2739<10000000, S2739>50000000), "Overperformer", "Normal")) -> Normal | AA2739: =VLOOKUP(D2739, lookups!$A$2:$B$18, 2, FALSE) -> High Budget | AB2739: =IF(AND(N2739>7, T2739>1, U2739>70), "Recommended", "Not Recommended") -> Not Recommended | AC2739: =IF(N2739>=8, "High Buzz / High Score", IF(AND(N2739<6, T2739<1), "High Buzz Mismatch", "Normal")) -> Normal
A2740: Kids | B2740: 35043 | C2740: Color | D2740: Drama | E2740: English | F2740: USA | H2740: Rosario Dawson | I2740: Larry Clark | J2740: 3000 | K2740: 3310 | L2740: 184 | M2740: 0 | N2740: 7 | O2740: 71 | P2740: 91 | Q2740: 7417210 | R2740: 1500000 | S2740: =Q2740-R2740 -> 5917210 | T2740: =IF(R2740>0, (Q2740-R2740)/R2740, 0) -> 3.9448067 | U2740: =(N2740*4) + (T2740*0.4) + (M2740/10000) -> 29.577923 | V2740: =YEAR(B2740) -> 1995 | W2740: =TEXT(B2740, "mmmm") -> dekabr | X2740: =TRIM(I2740) -> Larry Clark | Y2740: =UPPER(A2740) -> KİDS | Z2740: =IF(AND(R2740>50000000, S2740<0), "Underperformer", IF(AND(R2740<10000000, S2740>50000000), "Overperformer", "Normal")) -> Normal | AA2740: =VLOOKUP(D2740, lookups!$A$2:$B$18, 2, FALSE) -> Medium Budget | AB2740: =IF(AND(N2740>7, T2740>1, U2740>70), "Recommended", "Not Recommended") -> Not Recommended | AC2740: =IF(N2740>=8, "High Buzz / High Score", IF(AND(N2740<6, T2740<1), "High Buzz Mismatch", "Normal")) -> Normal
A2741: Doogal | B2741: 38752 | C2741: Color | D2741: Adventure | E2741: English | F2741: USA | G2741: G | H2741: Jimmy Fallon | I2741: Dave Borthwick | J2741: 787 | K2741: 2185 | L2741: 3 | M2741: 346 | N2741: 2.8 | O2741: 31 | P2741: 77 | Q2741: 7382993 | R2741: 20000000 | S2741: =Q2741-R2741 -> -12617007 | T2741: =IF(R2741>0, (Q2741-R2741)/R2741, 0) -> -0.63085035 | U2741: =(N2741*4) + (T2741*0.4) + (M2741/10000) -> 10.98226 | V2741: =YEAR(B2741) -> 2006 | W2741: =TEXT(B2741, "mmmm") -> fevral | X2741: =TRIM(I2741) -> Dave Borthwick | Y2741: =UPPER(A2741) -> DOOGAL | Z2741: =IF(AND(R2741>50000000, S2741<0), "Underperformer", IF(AND(R2741<10000000, S2741>50000000), "Overperformer", "Normal")) -> Normal | AA2741: =VLOOKUP(D2741, lookups!$A$2:$B$18, 2, FALSE) -> High Budget | AB2741: =IF(AND(N2741>7, T2741>1, U2741>70), "Recommended", "Not Recommended") -> Not Recommended | AC2741: =IF(N2741>=8, "High Buzz / High Score", IF(AND(N2741<6, T2741<1), "High Buzz Mismatch", "Normal")) -> High Buzz Mismatch
A2742: Witchboard | B2742: 31663 | C2742: Color | D2742: Horror | E2742: English | F2742: UK | G2742: R | H2742: Kathleen Wilhoite | I2742: Kevin Tenney | J2742: 265 | K2742: 901 | L2742: 85 | M2742: 0 | N2742: 5.7 | O2742: 65 | P2742: 98 | Q2742: 7369373 | R2742: 2000000 | S2742: =Q2742-R2742 -> 5369373 | T2742: =IF(R2742>0, (Q2742-R2742)/R2742, 0) -> 2.6846865 | U2742: =(N2742*4) + (T2742*0.4) + (M2742/10000) -> 23.873875 | V2742: =YEAR(B2742) -> 1986 | W2742: =TEXT(B2742, "mmmm") -> sentyabr | X2742: =TRIM(I2742) -> Kevin Tenney | Y2742: =UPPER(A2742) -> WİTCHBOARD | Z2742: =IF(AND(R2742>50000000, S2742<0), "Underperformer", IF(AND(R2742<10000000, S2742>50000000), "Overperformer", "Normal")) -> Normal | AA2742: =VLOOKUP(D2742, lookups!$A$2:$B$18, 2, FALSE) -> Low Budget | AB2742: =IF(AND(N2742>7, T2742>1, U2742>70), "Recommended", "Not Recommended") -> Not Recommended | AC2742: =IF(N2742>=8, "High Buzz / High Score", IF(AND(N2742<6, T2742<1), "High Buzz Mismatch", "Normal")) -> Normal
A2743: The Squid and the Whale | B2743: 38471 | C2743: Color | D2743: Comedy | E2743: English | F2743: USA | G2743: R | H2743: William Baldwin | I2743: Noah Baumbach | J2743: 436 | K2743: 479 | L2743: 387 | M2743: 0 | N2743: 7.4 | O2743: 110 | P2743: 88 | Q2743: 7362100 | R2743: 1500000 | S2743: =Q2743-R2743 -> 5862100 | T2743: =IF(R2743>0, (Q2743-R2743)/R2743, 0) -> 3.9080667 | U2743: =(N2743*4) + (T2743*0.4) + (M2743/10000) -> 31.163227 | V2743: =YEAR(B2743) -> 2005 | W2743: =TEXT(B2743, "mmmm") -> aprel | X2743: =TRIM(I2743) -> Noah Baumbach | Y2743: =UPPER(A2743) -> THE SQUİD AND THE WHALE | Z2743: =IF(AND(R2743>50000000, S2743<0), "Underperformer", IF(AND(R2743<10000000, S2743>50000000), "Overperformer", "Normal")) -> Normal | AA2743: =VLOOKUP(D2743, lookups!$A$2:$B$18, 2, FALSE) -> Medium Budget | AB2743: =IF(AND(N2743>7, T2743>1, U2743>70), "Recommended", "Not Recommended") -> Not Recommended | AC2743: =IF(N2743>=8, "High Buzz / High Score", IF(AND(N2743<6, T2743<1), "High Buzz Mismatch", "Normal")) -> Normal
A2744: Outside Providence | B2744: 36495 | C2744: Color | D2744: Comedy | E2744: English | F2744: USA | G2744: R | H2744: Jonathan Brandis | I2744: Michael Corrente | J2744: 761 | K2744: 2018 | L2744: 30 | M2744: 0 | N2744: 6.4 | O2744: 72 | P2744: 96 | Q2744: 7292175 | R2744: 7000000 | S2744: =Q2744-R2744 -> 292175 | T2744: =IF(R2744>0, (Q2744-R2744)/R2744, 0) -> 0.041739286 | U2744: =(N2744*4) + (T2744*0.4) + (M2744/10000) -> 25.616696 | V2744: =YEAR(B2744) -> 1999 | W2744: =TEXT(B2744, "mmmm") -> dekabr | X2744: =TRIM(I2744) -> Michael Corrente | Y2744: =UPPER(A2744) -> OUTSİDE PROVİDENCE | Z2744: =IF(AND(R2744>50000000, S2744<0), "Underperformer", IF(AND(R2744<10000000, S2744>50000000), "Overperformer", "Normal")) -> Normal | AA2744: =VLOOKUP(D2744, lookups!$A$2:$B$18, 2, FALSE) -> Medium Budget | AB2744: =IF(AND(N2744>7, T2744>1, U2744>70), "Recommended", "Not Recommended") -> Not Recommended | AC2744: =IF(N2744>=8, "High Buzz / High Score", IF(AND(N2744<6, T2744<1), "High Buzz Mismatch", "Normal")) -> Normal
A2745: Phantasm II | B2745: 32228 | C2745: Color | D2745: Action | E2745: English | F2745: USA | G2745: R | H2745: Angus Scrimm | I2745: Don Coscarelli | J2745: 674 | K2745: 1395 | L2745: 152 | M2745: 812 | N2745: 6.5 | O2745: 81 | P2745: 97 | Q2745: 7282851 | R2745: 3000000 | S2745: =Q2745-R2745 -> 4282851 | T2745: =IF(R2745>0, (Q2745-R2745)/R2745, 0) -> 1.427617 | U2745: =(N2745*4) + (T2745*0.4) + (M2745/10000) -> 26.652247 | V2745: =YEAR(B2745) -> 1988 | W2745: =TEXT(B2745, "mmmm") -> mart | X2745: =TRIM(I2745) -> Don Coscarelli | Y2745: =UPPER(A2745) -> PHANTASM II | Z2745: =IF(AND(R2745>50000000, S2745<0), "Underperformer", IF(AND(R2745<10000000, S2745>50000000), "Overperformer", "Normal")) -> Normal | AA2745: =VLOOKUP(D2745, lookups!$A$2:$B$18, 2, FALSE) -> High Budget | AB2745: =IF(AND(N2745>7, T2745>1, U2745>70), "Recommended", "Not Recommended") -> Not Recommended | AC2745: =IF(N2745>=8, "High Buzz / High Score", IF(AND(N2745<6, T2745<1), "High Buzz Mismatch", "Normal")) -> Normal
A2746: Machete Kills | B2746: 41474 | C2746: Color | D2746: Action | E2746: English | F2746: Russia | G2746: R | H2746: Alexa PenaVega | I2746: Robert Rodriguez | J2746: 2000 | K2746: 2848 | L2746: 0 | M2746: 48000 | N2746: 5.6 | O2746: 260 | P2746: 107 | Q2746: 7268659 | R2746: 20000000 | S2746: =Q2746-R2746 -> -12731341 | T2746: =IF(R2746>0, (Q2746-R2746)/R2746, 0) -> -0.63656705 | U2746: =(N2746*4) + (T2746*0.4) + (M2746/10000) -> 26.945373 | V2746: =YEAR(B2746) -> 2013 | W2746: =TEXT(B2746, "mmmm") -> iyul | X2746: =TRIM(I2746) -> Robert Rodriguez | Y2746: =UPPER(A2746) -> MACHETE KİLLS | Z2746: =IF(AND(R2746>50000000, S2746<0), "Underperformer", IF(AND(R2746<10000000, S2746>50000000), "Overperformer", "Normal")) -> Normal | AA2746: =VLOOKUP(D2746, lookups!$A$2:$B$18, 2, FALSE) -> High Budget | AB2746: =IF(AND(N2746>7, T2746>1, U2746>70), "Recommended", "Not Recommended") -> Not Recommended | AC2746: =IF(N2746>=8, "High Buzz / High Score", IF(AND(N2746<6, T2746<1), "High Buzz Mismatch", "Normal")) -> High Buzz Mismatch
A2747: Run Lola Run | B2747: 35893 | C2747: Black and White | D2747: Crime | E2747: German | F2747: Germany | G2747: R | H2747: Moritz Bleibtreu | I2747: Tom Tykwer | J2747: 486 | K2747: 623 | L2747: 670 | M2747: 0 | N2747: 7.8 | O2747: 181 | P2747: 81 | Q2747: 7267324 | R2747: 3500000 | S2747: =Q2747-R2747 -> 3767324 | T2747: =IF(R2747>0, (Q2747-R2747)/R2747, 0) -> 1.0763783 | U2747: =(N2747*4) + (T2747*0.4) + (M2747/10000) -> 31.630551 | V2747: =YEAR(B2747) -> 1998 | W2747: =TEXT(B2747, "mmmm") -> aprel | X2747: =TRIM(I2747) -> Tom Tykwer | Y2747: =UPPER(A2747) -> RUN LOLA RUN | Z2747: =IF(AND(R2747>50000000, S2747<0), "Underperformer", IF(AND(R2747<10000000, S2747>50000000), "Overperformer", "Normal")) -> Normal | AA2747: =VLOOKUP(D2747, lookups!$A$2:$B$18, 2, FALSE) -> Medium Budget | AB2747: =IF(AND(N2747>7, T2747>1, U2747>70), "Recommended", "Not Recommended") -> Not Recommended | AC2747: =IF(N2747>=8, "High Buzz / High Score", IF(AND(N2747<6, T2747<1), "High Buzz Mismatch", "Normal")) -> Normal
A2748: Big Trouble | B2748: 37372 | C2748: Color | D2748: Comedy | E2748: English | F2748: USA | G2748: PG-13 | H2748: Zooey Deschanel | I2748: Barry Sonnenfeld | J2748: 11000 | K2748: 13917 | L2748: 188 | M2748: 892 | N2748: 6.5 | O2748: 87 | P2748: 74 | Q2748: 7262288 | R2748: 40000000 | S2748: =Q2748-R2748 -> -32737712 | T2748: =IF(R2748>0, (Q2748-R2748)/R2748, 0) -> -0.8184428 | U2748: =(N2748*4) + (T2748*0.4) + (M2748/10000) -> 25.761823 | V2748: =YEAR(B2748) -> 2002 | W2748: =TEXT(B2748, "mmmm") -> aprel | X2748: =TRIM(I2748) -> Barry Sonnenfeld | Y2748: =UPPER(A2748) -> BİG TROUBLE | Z2748: =IF(AND(R2748>50000000, S2748<0), "Underperformer", IF(AND(R2748<10000000, S2748>50000000), "Overperformer", "Normal")) -> Normal | AA2748: =VLOOKUP(D2748, lookups!$A$2:$B$18, 2, FALSE) -> Medium Budget | AB2748: =IF(AND(N2748>7, T2748>1, U2748>70), "Recommended", "Not Recommended") -> Not Recommended | AC2748: =IF(N2748>=8, "High Buzz / High Score", IF(AND(N2748<6, T2748<1), "High Buzz Mismatch", "Normal")) -> Normal
A2749: All the King's Men | B2749: 39041 | C2749: Black and White | D2749: Drama | E2749: English | F2749: Germany | G2749: PG-13 | H2749: Kate Winslet | I2749: Steven Zaillian | J2749: 14000 | K2749: 27614 | L2749: 234 | M2749: 0 | N2749: 6.2 | O2749: 127 | P2749: 128 | Q2749: 7221458 | R2749: 55000000 | S2749: =Q2749-R2749 -> -47778542 | T2749: =IF(R2749>0, (Q2749-R2749)/R2749, 0) -> -0.86870076 | U2749: =(N2749*4) + (T2749*0.4) + (M2749/10000) -> 24.45252 | V2749: =YEAR(B2749) -> 2006 | W2749: =TEXT(B2749, "mmmm") -> noyabr | X2749: =TRIM(I2749) -> Steven Zaillian | Y2749: =UPPER(A2749) -> ALL THE KİNG'S MEN | Z2749: =IF(AND(R2749>50000000, S2749<0), "Underperformer", IF(AND(R2749<10000000, S2749>50000000), "Overperformer", "Normal")) -> Underperformer | AA2749: =VLOOKUP(D2749, lookups!$A$2:$B$18, 2, FALSE) -> Medium Budget | AB2749: =IF(AND(N2749>7, T2749>1, U2749>70), "Recommended", "Not Recommended") -> Not Recommended | AC2749: =IF(N2749>=8, "High Buzz / High Score", IF(AND(N2749<6, T2749<1), "High Buzz Mismatch", "Normal")) -> Normal
A2750: Mulholland Drive | B2750: 37192 | C2750: Color | D2750: Drama | E2750: English | F2750: France | G2750: R | H2750: Naomi Watts | I2750: David Lynch | J2750: 6000 | K2750: 8484 | L2750: 0 | M2750: 16000 | N2750: 8 | O2750: 252 | P2750: 147 | Q2750: 7219578 | R2750: 15000000 | S2750: =Q2750-R2750 -> -7780422 | T2750: =IF(R2750>0, (Q2750-R2750)/R2750, 0) -> -0.5186948 | U2750: =(N2750*4) + (T2750*0.4) + (M2750/10000) -> 33.392522 | V2750: =YEAR(B2750) -> 2001 | W2750: =TEXT(B2750, "mmmm") -> oktyabr | X2750: =TRIM(I2750) -> David Lynch | Y2750: =UPPER(A2750) -> MULHOLLAND DRİVE | Z2750: =IF(AND(R2750>50000000, S2750<0), "Underperformer", IF(AND(R2750<10000000, S2750>50000000), "Overperformer", "Normal")) -> Normal | AA2750: =VLOOKUP(D2750, lookups!$A$2:$B$18, 2, FALSE) -> Medium Budget | AB2750: =IF(AND(N2750>7, T2750>1, U2750>70), "Recommended", "Not Recommended") -> Not Recommended | AC2750: =IF(N2750>=8, "High Buzz / High Score", IF(AND(N2750<6, T2750<1), "High Buzz Mismatch", "Normal")) -> High Buzz / High Score
A2751: The Big Year | B2751: 40563 | C2751: Color | D2751: Comedy | E2751: English | F2751: USA | G2751: PG | H2751: Joel McHale | I2751: David Frankel | J2751: 734 | K2751: 2085 | L2751: 64 | M2751: 11000 | N2751: 6.2 | O2751: 108 | P2751: 100 | Q2751: 7204138 | R2751: 41000000 | S2751: =Q2751-R2751 -> -33795862 | T2751: =IF(R2751>0, (Q2751-R2751)/R2751, 0) -> -0.82428932 | U2751: =(N2751*4) + (T2751*0.4) + (M2751/10000) -> 25.570284 | V2751: =YEAR(B2751) -> 2011 | W2751: =TEXT(B2751, "mmmm") -> yanvar | X2751: =TRIM(I2751) -> David Frankel | Y2751: =UPPER(A2751) -> THE BİG YEAR | Z2751: =IF(AND(R2751>50000000, S2751<0), "Underperformer", IF(AND(R2751<10000000, S2751>50000000), "Overperformer", "Normal")) -> Normal | AA2751: =VLOOKUP(D2751, lookups!$A$2:$B$18, 2, FALSE) -> Medium Budget | AB2751: =IF(AND(N2751>7, T2751>1, U2751>70), "Recommended", "Not Recommended") -> Not Recommended | AC2751: =IF(N2751>=8, "High Buzz / High Score", IF(AND(N2751<6, T2751<1), "High Buzz Mismatch", "Normal")) -> Normal
A2752: The Green Inferno | B2752: 41292 | C2752: Color | D2752: Adventure | E2752: English | F2752: USA | G2752: R | H2752: Daryl Sabara | I2752: Eli Roth | J2752: 640 | K2752: 2082 | L2752: 0 | M2752: 12000 | N2752: 5.4 | O2752: 285 | P2752: 100 | Q2752: 7186670 | R2752: 6000000 | S2752: =Q2752-R2752 -> 1186670 | T2752: =IF(R2752>0, (Q2752-R2752)/R2752, 0) -> 0.19777833 | U2752: =(N2752*4) + (T2752*0.4) + (M2752/10000) -> 22.879111 | V2752: =YEAR(B2752) -> 2013 | W2752: =TEXT(B2752, "mmmm") -> yanvar | X2752: =TRIM(I2752) -> Eli Roth | Y2752: =UPPER(A2752) -> THE GREEN INFERNO | Z2752: =IF(AND(R2752>50000000, S2752<0), "Underperformer", IF(AND(R2752<10000000, S2752>50000000), "Overperformer", "Normal")) -> Normal | AA2752: =VLOOKUP(D2752, lookups!$A$2:$B$18, 2, FALSE) -> High Budget | AB2752: =IF(AND(N2752>7, T2752>1, U2752>70), "Recommended", "Not Recommended") -> Not Recommended | AC2752: =IF(N2752>=8, "High Buzz / High Score", IF(AND(N2752<6, T2752<1), "High Buzz Mismatch", "Normal")) -> High Buzz Mismatch
... A2797: Maria Full of Grace | B2797: 38215 | C2797: Color | D2797: Crime | E2797: Spanish | F2797: Colombia | G2797: R | H2797: Catalina Sandino Moreno | I2797: Joshua Marston | J2797: 280 | K2797: 308 | L2797: 13 | M2797: 0 | N2797: 7.5 | O2797: 155 | P2797: 101 | Q2797: 6517198 | R2797: 3000000 | S2797: =Q2797-R2797 -> 3517198 | T2797: =IF(R2797>0, (Q2797-R2797)/R2797, 0) -> 1.1723993 | U2797: =(N2797*4) + (T2797*0.4) + (M2797/10000) -> 30.46896 | V2797: =YEAR(B2797) -> 2004 | W2797: =TEXT(B2797, "mmmm") -> avgust | X2797: =TRIM(I2797) -> Joshua Marston | Y2797: =UPPER(A2797) -> MARİA FULL OF GRACE | Z2797: =IF(AND(R2797>50000000, S2797<0), "Underperformer", IF(AND(R2797<10000000, S2797>50000000), "Overperformer", "Normal")) -> Normal | AA2797: =VLOOKUP(D2797, lookups!$A$2:$B$18, 2, FALSE) -> Medium Budget | AB2797: =IF(AND(N2797>7, T2797>1, U2797>70), "Recommended", "Not Recommended") -> Not Recommended | AC2797: =IF(N2797>=8, "High Buzz / High Score", IF(AND(N2797<6, T2797<1), "High Buzz Mismatch", "Normal")) -> Normal
A2798: Baahubali: The Beginning | B2798: 42182 | C2798: Color | D2798: Action | E2798: Telugu | F2798: India | H2798: Tamannaah Bhatia | I2798: S.S. Rajamouli | J2798: 218 | K2798: 554 | L2798: 50 | M2798: 21000 | N2798: 8.4 | O2798: 44 | P2798: 159 | Q2798: 6498000 | R2798: 18026148 | S2798: =Q2798-R2798 -> -11528148 | T2798: =IF(R2798>0, (Q2798-R2798)/R2798, 0) -> -0.63952365 | U2798: =(N2798*4) + (T2798*0.4) + (M2798/10000) -> 35.444191 | V2798: =YEAR(B2798) -> 2015 | W2798: =TEXT(B2798, "mmmm") -> iyun | X2798: =TRIM(I2798) -> S.S. Rajamouli | Y2798: =UPPER(A2798) -> BAAHUBALİ: THE BEGİNNİNG | Z2798: =IF(AND(R2798>50000000, S2798<0), "Underperformer", IF(AND(R2798<10000000, S2798>50000000), "Overperformer", "Normal")) -> Normal | AA2798: =VLOOKUP(D2798, lookups!$A$2:$B$18, 2, FALSE) -> High Budget | AB2798: =IF(AND(N2798>7, T2798>1, U2798>70), "Recommended", "Not Recommended") -> Not Recommended | AC2798: =IF(N2798>=8, "High Buzz / High Score", IF(AND(N2798<6, T2798<1), "High Buzz Mismatch", "Normal")) -> High Buzz / High Score
A2799: Teacher's Pet | B2799: 38101 | C2799: Color | D2799: Animation | E2799: English | F2799: USA | G2799: PG | H2799: Nathan Lane | I2799: Timothy BjÃ¶rklund | J2799: 886 | K2799: 5139 | L2799: 0 | M2799: 49 | N2799: 5.8 | O2799: 33 | P2799: 74 | Q2799: 6491350 | R2799: 10000000 | S2799: =Q2799-R2799 -> -3508650 | T2799: =IF(R2799>0, (Q2799-R2799)/R2799, 0) -> -0.350865 | U2799: =(N2799*4) + (T2799*0.4) + (M2799/10000) -> 23.064554 | V2799: =YEAR(B2799) -> 2004 | W2799: =TEXT(B2799, "mmmm") -> aprel | X2799: =TRIM(I2799) -> Timothy BjÃ¶rklund | Y2799: =UPPER(A2799) -> TEACHER'S PET | Z2799: =IF(AND(R2799>50000000, S2799<0), "Underperformer", IF(AND(R2799<10000000, S2799>50000000), "Overperformer", "Normal")) -> Normal | AA2799: =VLOOKUP(D2799, lookups!$A$2:$B$18, 2, FALSE) -> High Budget | AB2799: =IF(AND(N2799>7, T2799>1, U2799>70), "Recommended", "Not Recommended") -> Not Recommended | AC2799: =IF(N2799>=8, "High Buzz / High Score", IF(AND(N2799<6, T2799<1), "High Buzz Mismatch", "Normal")) -> High Buzz Mismatch
A2800: Switchback | B2800: 35640 | C2800: Color | D2800: Crime | E2800: English | F2800: USA | G2800: R | H2800: Gregory Scott Cummins | I2800: Jeb Stuart | J2800: 37 | K2800: 74 | L2800: 11 | M2800: 389 | N2800: 6.4 | O2800: 38 | P2800: 118 | Q2800: 6482195 | R2800: 37000000 | S2800: =Q2800-R2800 -> -30517805 | T2800: =IF(R2800>0, (Q2800-R2800)/R2800, 0) -> -0.82480554 | U2800: =(N2800*4) + (T2800*0.4) + (M2800/10000) -> 25.308978 | V2800: =YEAR(B2800) -> 1997 | W2800: =TEXT(B2800, "mmmm") -> iyul | X2800: =TRIM(I2800) -> Jeb Stuart | Y2800: =UPPER(A2800) -> SWİTCHBACK | Z2800: =IF(AND(R2800>50000000, S2800<0), "Underperformer", IF(AND(R2800<10000000, S2800>50000000), "Overperformer", "Normal")) -> Normal | AA2800: =VLOOKUP(D2800, lookups!$A$2:$B$18, 2, FALSE) -> Medium Budget | AB2800: =IF(AND(N2800>7, T2800>1, U2800>70), "Recommended", "Not Recommended") -> Not Recommended | AC2800: =IF(N2800>=8, "High Buzz / High Score", IF(AND(N2800<6, T2800<1), "High Buzz Mismatch", "Normal")) -> Normal
A2801: The Big Bounce | B2801: 38234 | C2801: Color | D2801: Comedy | E2801: English | F2801: USA | G2801: PG-13 | H2801: Morgan Freeman | I2801: George Armitage | J2801: 11000 | K2801: 11972 | L2801: 5 | M2801: 288 | N2801: 4.9 | O2801: 75 | P2801: 88 | Q2801: 6471394 | R2801: 50000000 | S2801: =Q2801-R2801 -> -43528606 | T2801: =IF(R2801>0, (Q2801-R2801)/R2801, 0) -> -0.87057212 | U2801: =(N2801*4) + (T2801*0.4) + (M2801/10000) -> 19.280571 | V2801: =YEAR(B2801) -> 2004 | W2801: =TEXT(B2801, "mmmm") -> sentyabr | X2801: =TRIM(I2801) -> George Armitage | Y2801: =UPPER(A2801) -> THE BİG BOUNCE | Z2801: =IF(AND(R2801>50000000, S2801<0), "Underperformer", IF(AND(R2801<10000000, S2801>50000000), "Overperformer", "Normal")) -> Normal | AA2801: =VLOOKUP(D2801, lookups!$A$2:$B$18, 2, FALSE) -> Medium Budget | AB2801: =IF(AND(N2801>7, T2801>1, U2801>70), "Recommended", "Not Recommended") -> Not Recommended | AC2801: =IF(N2801>=8, "High Buzz / High Score", IF(AND(N2801<6, T2801<1), "High Buzz Mismatch", "Normal")) -> High Buzz Mismatch
A2802: Warriors of Virtue | B2802: 35431 | C2802: Color | D2802: Action | E2802: English | F2802: USA | G2802: PG | H2802: Marley Shelton | I2802: Ronny Yu | J2802: 690 | K2802: 1993 | L2802: 31 | M2802: 0 | N2802: 4.6 | O2802: 24 | P2802: 101 | Q2802: 6448817 | R2802: 35000000 | S2802: =Q2802-R2802 -> -28551183 | T2802: =IF(R2802>0, (Q2802-R2802)/R2802, 0) -> -0.81574809 | U2802: =(N2802*4) + (T2802*0.4) + (M2802/10000) -> 18.073701 | V2802: =YEAR(B2802) -> 1997 | W2802: =TEXT(B2802, "mmmm") -> yanvar | X2802: =TRIM(I2802) -> Ronny Yu | Y2802: =UPPER(A2802) -> WARRİORS OF VİRTUE | Z2802: =IF(AND(R2802>50000000, S2802<0), "Underperformer", IF(AND(R2802<10000000, S2802>50000000), "Overperformer", "Normal")) -> Normal | AA2802: =VLOOKUP(D2802, lookups!$A$2:$B$18, 2, FALSE) -> High Budget | AB2802: =IF(AND(N2802>7, T2802>1, U2802>70), "Recommended", "Not Recommended") -> Not Recommended | AC2802: =IF(N2802>=8, "High Buzz / High Score", IF(AND(N2802<6, T2802<1), "High Buzz Mismatch", "Normal")) -> High Buzz Mismatch
A2803: Little Boy | B2803: 42059 | C2803: Color | D2803: Drama | E2803: English | F2803: Mexico | G2803: PG-13 | H2803: Tom Wilkinson | I2803: Alejandro Monteverde | J2803: 1000 | K2803: 5705 | L2803: 38 | M2803: 15000 | N2803: 7.4 | O2803: 45 | P2803: 106 | Q2803: 6420319 | R2803: 20000000 | S2803: =Q2803-R2803 -> -13579681 | T2803: =IF(R2803>0, (Q2803-R2803)/R2803, 0) -> -0.67898405 | U2803: =(N2803*4) + (T2803*0.4) + (M2803/10000) -> 30.828406 | V2803: =YEAR(B2803) -> 2015 | W2803: =TEXT(B2803, "mmmm") -> fevral | X2803: =TRIM(I2803) -> Alejandro Monteverde | Y2803: =UPPER(A2803) -> LİTTLE BOY | Z2803: =IF(AND(R2803>50000000, S2803<0), "Underperformer", IF(AND(R2803<10000000, S2803>50000000), "Overperformer", "Normal")) -> Normal | AA2803: =VLOOKUP(D2803, lookups!$A$2:$B$18, 2, FALSE) -> Medium Budget | AB2803: =IF(AND(N2803>7, T2803>1, U2803>70), "Recommended", "Not Recommended") -> Not Recommended | AC2803: =IF(N2803>=8, "High Buzz / High Score", IF(AND(N2803<6, T2803<1), "High Buzz Mismatch", "Normal")) -> Normal
A2804: The Rocker | B2804: 39790 | C2804: Color | D2804: Comedy | E2804: English | F2804: USA | G2804: PG-13 | H2804: Emma Stone | I2804: Peter Cattaneo | J2804: 15000 | K2804: 33153 | L2804: 11 | M2804: 0 | N2804: 6.2 | O2804: 132 | P2804: 102 | Q2804: 6409206 | R2804: 15000000 | S2804: =Q2804-R2804 -> -8590794 | T2804: =IF(R2804>0, (Q2804-R2804)/R2804, 0) -> -0.5727196 | U2804: =(N2804*4) + (T2804*0.4) + (M2804/10000) -> 24.570912 | V2804: =YEAR(B2804) -> 2008 | W2804: =TEXT(B2804, "mmmm") -> dekabr | X2804: =TRIM(I2804) -> Peter Cattaneo | Y2804: =UPPER(A2804) -> THE ROCKER | Z2804: =IF(AND(R2804>50000000, S2804<0), "Underperformer", IF(AND(R2804<10000000, S2804>50000000), "Overperformer", "Normal")) -> Normal | AA2804: =VLOOKUP(D2804, lookups!$A$2:$B$18, 2, FALSE) -> Medium Budget | AB2804: =IF(AND(N2804>7, T2804>1, U2804>70), "Recommended", "Not Recommended") -> Not Recommended | AC2804: =IF(N2804>=8, "High Buzz / High Score", IF(AND(N2804<6, T2804<1), "High Buzz Mismatch", "Normal")) -> Normal
A2805: My Own Private Idaho | B2805: 33585 | C2805: Color | D2805: Drama | E2805: English | F2805: USA | G2805: R | H2805: Keanu Reeves | I2805: Gus Van Sant | J2805: 18000 | K2805: 19923 | L2805: 835 | M2805: 0 | N2805: 7.1 | O2805: 63 | P2805: 104 | Q2805: 6401336 | R2805: 2500000 | S2805: =Q2805-R2805 -> 3901336 | T2805: =IF(R2805>0, (Q2805-R2805)/R2805, 0) -> 1.5605344 | U2805: =(N2805*4) + (T2805*0.4) + (M2805/10000) -> 29.024214 | V2805: =YEAR(B2805) -> 1991 | W2805: =TEXT(B2805, "mmmm") -> dekabr | X2805: =TRIM(I2805) -> Gus Van Sant | Y2805: =UPPER(A2805) -> MY OWN PRİVATE IDAHO | Z2805: =IF(AND(R2805>50000000, S2805<0), "Underperformer", IF(AND(R2805<10000000, S2805>50000000), "Overperformer", "Normal")) -> Normal | AA2805: =VLOOKUP(D2805, lookups!$A$2:$B$18, 2, FALSE) -> Medium Budget | AB2805: =IF(AND(N2805>7, T2805>1, U2805>70), "Recommended", "Not Recommended") -> Not Recommended | AC2805: =IF(N2805>=8, "High Buzz / High Score", IF(AND(N2805<6, T2805<1), "High Buzz Mismatch", "Normal")) -> Normal
A2806: Gods and Monsters | B2806: 36157 | C2806: Black and White | D2806: Biography | E2806: English | F2806: USA | G2806: R | H2806: Brendan Fraser | I2806: Bill Condon | J2806: 3000 | K2806: 4238 | L2806: 386 | M2806: 0 | N2806: 7.5 | O2806: 127 | P2806: 105 | Q2806: 6390032 | R2806: 3500000 | S2806: =Q2806-R2806 -> 2890032 | T2806: =IF(R2806>0, (Q2806-R2806)/R2806, 0) -> 0.82572343 | U2806: =(N2806*4) + (T2806*0.4) + (M2806/10000) -> 30.330289 | V2806: =YEAR(B2806) -> 1998 | W2806: =TEXT(B2806, "mmmm") -> dekabr | X2806: =TRIM(I2806) -> Bill Condon | Y2806: =UPPER(A2806) -> GODS AND MONSTERS | Z2806: =IF(AND(R2806>50000000, S2806<0), "Underperformer", IF(AND(R2806<10000000, S2806>50000000), "Overperformer", "Normal")) -> Normal | AA2806: =VLOOKUP(D2806, lookups!$A$2:$B$18, 2, FALSE) -> Medium Budget | AB2806: =IF(AND(N2806>7, T2806>1, U2806>70), "Recommended", "Not Recommended") -> Not Recommended | AC2806: =IF(N2806>=8, "High Buzz / High Score", IF(AND(N2806<6, T2806<1), "High Buzz Mismatch", "Normal")) -> Normal
A2807: Post Grad | B2807: 39851 | C2807: Color | D2807: Comedy | E2807: English | F2807: USA | G2807: PG-13 | H2807: J.K. Simmons | I2807: Vicky Jenson | J2807: 24000 | K2807: 25637 | L2807: 96 | M2807: 0 | N2807: 5.3 | O2807: 97 | P2807: 88 | Q2807: 6373693 | R2807: 15000000 | S2807: =Q2807-R2807 -> -8626307 | T2807: =IF(R2807>0, (Q2807-R2807)/R2807, 0) -> -0.57508713 | U2807: =(N2807*4) + (T2807*0.4) + (M2807/10000) -> 20.969965 | V2807: =YEAR(B2807) -> 2009 | W2807: =TEXT(B2807, "mmmm") -> fevral | X2807: =TRIM(I2807) -> Vicky Jenson | Y2807: =UPPER(A2807) -> POST GRAD | Z2807: =IF(AND(R2807>50000000, S2807<0), "Underperformer", IF(AND(R2807<10000000, S2807>50000000), "Overperformer", "Normal")) -> Normal | AA2807: =VLOOKUP(D2807, lookups!$A$2:$B$18, 2, FALSE) -> Medium Budget | AB2807: =IF(AND(N2807>7, T2807>1, U2807>70), "Recommended", "Not Recommended") -> Not Recommended | AC2807: =IF(N2807>=8, "High Buzz / High Score", IF(AND(N2807<6, T2807<1), "High Buzz Mismatch", "Normal")) -> High Buzz Mismatch
A2808: It's Kind of a Funny Story | B2808: 40388 | C2808: Color | D2808: Comedy | E2808: English | F2808: USA | G2808: PG-13 | H2808: ZoÃ« Kravitz | I2808: Anna Boden | J2808: 943 | K2808: 2786 | L2808: 16 | M2808: 20000 | N2808: 7.2 | O2808: 163 | P2808: 101 | Q2808: 6350058 | R2808: 8000000 | S2808: =Q2808-R2808 -> -1649942 | T2808: =IF(R2808>0, (Q2808-R2808)/R2808, 0) -> -0.20624275 | U2808: =(N2808*4) + (T2808*0.4) + (M2808/10000) -> 30.717503 | V2808: =YEAR(B2808) -> 2010 | W2808: =TEXT(B2808, "mmmm") -> iyul | X2808: =TRIM(I2808) -> Anna Boden | Y2808: =UPPER(A2808) -> IT'S KİND OF A FUNNY STORY | Z2808: =IF(AND(R2808>50000000, S2808<0), "Underperformer", IF(AND(R2808<10000000, S2808>50000000), "Overperformer", "Normal")) -> Normal | AA2808: =VLOOKUP(D2808, lookups!$A$2:$B$18, 2, FALSE) -> Medium Budget | AB2808: =IF(AND(N2808>7, T2808>1, U2808>70), "Recommended", "Not Recommended") -> Not Recommended | AC2808: =IF(N2808>=8, "High Buzz / High Score", IF(AND(N2808<6, T2808<1), "High Buzz Mismatch", "Normal")) -> Normal
A2809: The Jacket | B2809: 38636 | C2809: Color | D2809: Drama | E2809: English | F2809: USA | G2809: R | H2809: Jennifer Jason Leigh | I2809: John Maybury | J2809: 1000 | K2809: 5085 | L2809: 11 | M2809: 0 | N2809: 7.1 | O2809: 161 | P2809: 94 | Q2809: 6301131 | R2809: 29000000 | S2809: =Q2809-R2809 -> -22698869 | T2809: =IF(R2809>0, (Q2809-R2809)/R2809, 0) -> -0.78271962 | U2809: =(N2809*4) + (T2809*0.4) + (M2809/10000) -> 28.086912 | V2809: =YEAR(B2809) -> 2005 | W2809: =TEXT(B2809, "mmmm") -> oktyabr | X2809: =TRIM(I2809) -> John Maybury | Y2809: =UPPER(A2809) -> THE JACKET | Z2809: =IF(AND(R2809>50000000, S2809<0), "Underperformer", IF(AND(R2809<10000000, S2809>50000000), "Overperformer", "Normal")) -> Normal | AA2809: =VLOOKUP(D2809, lookups!$A$2:$B$18, 2, FALSE) -> Medium Budget | AB2809: =IF(AND(N2809>7, T2809>1, U2809>70), "Recommended", "Not Recommended") -> Not Recommended | AC2809: =IF(N2809>=8, "High Buzz / High Score", IF(AND(N2809<6, T2809<1), "High Buzz Mismatch", "Normal")) -> Normal
A2810: What Planet Are You From? | B2810: 36782 | C2810: Color | D2810: Comedy | E2810: English | F2810: USA | G2810: R | H2810: Judy Greer | I2810: Mike Nichols | J2810: 2000 | K2810: 3954 | L2810: 0 | M2810: 255 | N2810: 5.6 | O2810: 82 | P2810: 87 | Q2810: 6291602 | R2810: 50000000 | S2810: =Q2810-R2810 -> -43708398 | T2810: =IF(R2810>0, (Q2810-R2810)/R2810, 0) -> -0.87416796 | U2810: =(N2810*4) + (T2810*0.4) + (M2810/10000) -> 22.075833 | V2810: =YEAR(B2810) -> 2000 | W2810: =TEXT(B2810, "mmmm") -> sentyabr | X2810: =TRIM(I2810) -> Mike Nichols | Y2810: =UPPER(A2810) -> WHAT PLANET ARE YOU FROM? | Z2810: =IF(AND(R2810>50000000, S2810<0), "Underperformer", IF(AND(R2810<10000000, S2810>50000000), "Overperformer", "Normal")) -> Normal | AA2810: =VLOOKUP(D2810, lookups!$A$2:$B$18, 2, FALSE) -> Medium Budget | AB2810: =IF(AND(N2810>7, T2810>1, U2810>70), "Recommended", "Not Recommended") -> Not Recommended | AC2810: =IF(N2810>=8, "High Buzz / High Score", IF(AND(N2810<6, T2810<1), "High Buzz Mismatch", "Normal")) -> High Buzz Mismatch
... A2973: The Raid: Redemption | B2973: 40652 | C2973: Color | D2973: Action | E2973: Indonesian | F2973: Indonesia | G2973: R | H2973: Iko Uwais | I2973: Gareth Evans | J2973: 1000 | K2973: 1445 | L2973: 338 | M2973: 51000 | N2973: 7.6 | O2973: 481 | P2973: 102 | Q2973: 4105123 | R2973: 1100000 | S2973: =Q2973-R2973 -> 3005123 | T2973: =IF(R2973>0, (Q2973-R2973)/R2973, 0) -> 2.73193 | U2973: =(N2973*4) + (T2973*0.4) + (M2973/10000) -> 36.592772 | V2973: =YEAR(B2973) -> 2011 | W2973: =TEXT(B2973, "mmmm") -> aprel | X2973: =TRIM(I2973) -> Gareth Evans | Y2973: =UPPER(A2973) -> THE RAİD: REDEMPTİON | Z2973: =IF(AND(R2973>50000000, S2973<0), "Underperformer", IF(AND(R2973<10000000, S2973>50000000), "Overperformer", "Normal")) -> Normal | AA2973: =VLOOKUP(D2973, lookups!$A$2:$B$18, 2, FALSE) -> High Budget | AB2973: =IF(AND(N2973>7, T2973>1, U2973>70), "Recommended", "Not Recommended") -> Not Recommended | AC2973: =IF(N2973>=8, "High Buzz / High Score", IF(AND(N2973<6, T2973<1), "High Buzz Mismatch", "Normal")) -> Normal
A2974: Sea Rex 3D: Journey to a Prehistoric World | B2974: 40388 | C2974: Color | D2974: Documentary | E2974: English | F2974: UK | H2974: Norbert Ferrer | I2974: Ronan Chapalain | J2974: 55 | K2974: 55 | L2974: 0 | M2974: 89 | N2974: 6.9 | O2974: 7 | P2974: 41 | Q2974: 4074023 | R2974: 5000000 | S2974: =Q2974-R2974 -> -925977 | T2974: =IF(R2974>0, (Q2974-R2974)/R2974, 0) -> -0.1851954 | U2974: =(N2974*4) + (T2974*0.4) + (M2974/10000) -> 27.534822 | V2974: =YEAR(B2974) -> 2010 | W2974: =TEXT(B2974, "mmmm") -> iyul | X2974: =TRIM(I2974) -> Ronan Chapalain | Y2974: =UPPER(A2974) -> SEA REX 3D: JOURNEY TO A PREHİSTORİC WORLD | Z2974: =IF(AND(R2974>50000000, S2974<0), "Underperformer", IF(AND(R2974<10000000, S2974>50000000), "Overperformer", "Normal")) -> Normal | AA2974: =VLOOKUP(D2974, lookups!$A$2:$B$18, 2, FALSE) -> Low Budget | AB2974: =IF(AND(N2974>7, T2974>1, U2974>70), "Recommended", "Not Recommended") -> Not Recommended | AC2974: =IF(N2974>=8, "High Buzz / High Score", IF(AND(N2974<6, T2974<1), "High Buzz Mismatch", "Normal")) -> Normal
A2975: The Visual Bible: The Gospel of John | B2975: 37759 | C2975: Color | D2975: Biography | E2975: English | F2975: Canada | G2975: PG-13 | H2975: Henry Ian Cusick | I2975: Philip Saville | J2975: 866 | K2975: 1281 | L2975: 10 | M2975: 0 | N2975: 7.7 | O2975: 25 | P2975: 125 | Q2975: 4068087 | R2975: 17000000 | S2975: =Q2975-R2975 -> -12931913 | T2975: =IF(R2975>0, (Q2975-R2975)/R2975, 0) -> -0.76070076 | U2975: =(N2975*4) + (T2975*0.4) + (M2975/10000) -> 30.49572 | V2975: =YEAR(B2975) -> 2003 | W2975: =TEXT(B2975, "mmmm") -> may | X2975: =TRIM(I2975) -> Philip Saville | Y2975: =UPPER(A2975) -> THE VİSUAL BİBLE: THE GOSPEL OF JOHN | Z2975: =IF(AND(R2975>50000000, S2975<0), "Underperformer", IF(AND(R2975<10000000, S2975>50000000), "Overperformer", "Normal")) -> Normal | AA2975: =VLOOKUP(D2975, lookups!$A$2:$B$18, 2, FALSE) -> Medium Budget | AB2975: =IF(AND(N2975>7, T2975>1, U2975>70), "Recommended", "Not Recommended") -> Not Recommended | AC2975: =IF(N2975>=8, "High Buzz / High Score", IF(AND(N2975<6, T2975<1), "High Buzz Mismatch", "Normal")) -> Normal
A2976: Tank Girl | B2976: 34894 | C2976: Color | D2976: Action | E2976: English | F2976: USA | G2976: R | H2976: Naomi Watts | I2976: Rachel Talalay | J2976: 6000 | K2976: 9662 | L2976: 54 | M2976: 0 | N2976: 5.2 | O2976: 60 | P2976: 104 | Q2976: 4064333 | R2976: 25000000 | S2976: =Q2976-R2976 -> -20935667 | T2976: =IF(R2976>0, (Q2976-R2976)/R2976, 0) -> -0.83742668 | U2976: =(N2976*4) + (T2976*0.4) + (M2976/10000) -> 20.465029 | V2976: =YEAR(B2976) -> 1995 | W2976: =TEXT(B2976, "mmmm") -> iyul | X2976: =TRIM(I2976) -> Rachel Talalay | Y2976: =UPPER(A2976) -> TANK GİRL | Z2976: =IF(AND(R2976>50000000, S2976<0), "Underperformer", IF(AND(R2976<10000000, S2976>50000000), "Overperformer", "Normal")) -> Normal | AA2976: =VLOOKUP(D2976, lookups!$A$2:$B$18, 2, FALSE) -> High Budget | AB2976: =IF(AND(N2976>7, T2976>1, U2976>70), "Recommended", "Not Recommended") -> Not Recommended | AC2976: =IF(N2976>=8, "High Buzz / High Score", IF(AND(N2976<6, T2976<1), "High Buzz Mismatch", "Normal")) -> High Buzz Mismatch
A2977: Good Bye Lenin! | B2977: 37872 | C2977: Black and White | D2977: Drama | E2977: German | F2977: Germany | G2977: R | H2977: Florian Lukas | I2977: Wolfgang Becker | J2977: 65 | K2977: 200 | L2977: 31 | M2977: 11000 | N2977: 7.7 | O2977: 153 | P2977: 121 | Q2977: 4063859 | R2977: 4800000 | S2977: =Q2977-R2977 -> -736141 | T2977: =IF(R2977>0, (Q2977-R2977)/R2977, 0) -> -0.15336271 | U2977: =(N2977*4) + (T2977*0.4) + (M2977/10000) -> 31.838655 | V2977: =YEAR(B2977) -> 2003 | W2977: =TEXT(B2977, "mmmm") -> sentyabr | X2977: =TRIM(I2977) -> Wolfgang Becker | Y2977: =UPPER(A2977) -> GOOD BYE LENİN! | Z2977: =IF(AND(R2977>50000000, S2977<0), "Underperformer", IF(AND(R2977<10000000, S2977>50000000), "Overperformer", "Normal")) -> Normal | AA2977: =VLOOKUP(D2977, lookups!$A$2:$B$18, 2, FALSE) -> Medium Budget | AB2977: =IF(AND(N2977>7, T2977>1, U2977>70), "Recommended", "Not Recommended") -> Not Recommended | AC2977: =IF(N2977>=8, "High Buzz / High Score", IF(AND(N2977<6, T2977<1), "High Buzz Mismatch", "Normal")) -> Normal
A2978: Secretary | B2978: 37487 | C2978: Color | D2978: Comedy | E2978: English | F2978: USA | G2978: R | H2978: Jeremy Davies | I2978: Steven Shainberg | J2978: 769 | K2978: 2251 | L2978: 30 | M2978: 15000 | N2978: 7.1 | O2978: 163 | P2978: 104 | Q2978: 4046737 | R2978: 4000000 | S2978: =Q2978-R2978 -> 46737 | T2978: =IF(R2978>0, (Q2978-R2978)/R2978, 0) -> 0.01168425 | U2978: =(N2978*4) + (T2978*0.4) + (M2978/10000) -> 29.904674 | V2978: =YEAR(B2978) -> 2002 | W2978: =TEXT(B2978, "mmmm") -> avgust | X2978: =TRIM(I2978) -> Steven Shainberg | Y2978: =UPPER(A2978) -> SECRETARY | Z2978: =IF(AND(R2978>50000000, S2978<0), "Underperformer", IF(AND(R2978<10000000, S2978>50000000), "Overperformer", "Normal")) -> Normal | AA2978: =VLOOKUP(D2978, lookups!$A$2:$B$18, 2, FALSE) -> Medium Budget | AB2978: =IF(AND(N2978>7, T2978>1, U2978>70), "Recommended", "Not Recommended") -> Not Recommended | AC2978: =IF(N2978>=8, "High Buzz / High Score", IF(AND(N2978<6, T2978<1), "High Buzz Mismatch", "Normal")) -> Normal
A2979: Bottle Shock | B2979: 39728 | C2979: Color | D2979: Comedy | E2979: English | F2979: USA | G2979: PG-13 | H2979: Alan Rickman | I2979: Randall Miller | J2979: 25000 | K2979: 25676 | L2979: 19 | M2979: 0 | N2979: 6.8 | O2979: 109 | P2979: 110 | Q2979: 4040588 | R2979: 5000000 | S2979: =Q2979-R2979 -> -959412 | T2979: =IF(R2979>0, (Q2979-R2979)/R2979, 0) -> -0.1918824 | U2979: =(N2979*4) + (T2979*0.4) + (M2979/10000) -> 27.123247 | V2979: =YEAR(B2979) -> 2008 | W2979: =TEXT(B2979, "mmmm") -> oktyabr | X2979: =TRIM(I2979) -> Randall Miller | Y2979: =UPPER(A2979) -> BOTTLE SHOCK | Z2979: =IF(AND(R2979>50000000, S2979<0), "Underperformer", IF(AND(R2979<10000000, S2979>50000000), "Overperformer", "Normal")) -> Normal | AA2979: =VLOOKUP(D2979, lookups!$A$2:$B$18, 2, FALSE) -> Medium Budget | AB2979: =IF(AND(N2979>7, T2979>1, U2979>70), "Recommended", "Not Recommended") -> Not Recommended | AC2979: =IF(N2979>=8, "High Buzz / High Score", IF(AND(N2979<6, T2979<1), "High Buzz Mismatch", "Normal")) -> Normal
A2980: My Name Is Khan | B2980: 40286 | C2980: Color | D2980: Adventure | E2980: Hindi | F2980: India | G2980: PG-13 | H2980: Shah Rukh Khan | I2980: Karan Johar | J2980: 8000 | K2980: 8532 | L2980: 160 | M2980: 27000 | N2980: 8 | O2980: 210 | P2980: 128 | Q2980: 4018695 | R2980: 12000000 | S2980: =Q2980-R2980 -> -7981305 | T2980: =IF(R2980>0, (Q2980-R2980)/R2980, 0) -> -0.66510875 | U2980: =(N2980*4) + (T2980*0.4) + (M2980/10000) -> 34.433957 | V2980: =YEAR(B2980) -> 2010 | W2980: =TEXT(B2980, "mmmm") -> aprel | X2980: =TRIM(I2980) -> Karan Johar | Y2980: =UPPER(A2980) -> MY NAME IS KHAN | Z2980: =IF(AND(R2980>50000000, S2980<0), "Underperformer", IF(AND(R2980<10000000, S2980>50000000), "Overperformer", "Normal")) -> Normal | AA2980: =VLOOKUP(D2980, lookups!$A$2:$B$18, 2, FALSE) -> High Budget | AB2980: =IF(AND(N2980>7, T2980>1, U2980>70), "Recommended", "Not Recommended") -> Not Recommended | AC2980: =IF(N2980>=8, "High Buzz / High Score", IF(AND(N2980<6, T2980<1), "High Buzz Mismatch", "Normal")) -> High Buzz / High Score
A2981: Safety Not Guaranteed | B2981: 41080 | C2981: Color | D2981: Comedy | E2981: English | F2981: USA | G2981: R | H2981: Mary Lynn Rajskub | I2981: Colin Trevorrow | J2981: 934 | K2981: 2714 | L2981: 365 | M2981: 31000 | N2981: 7 | O2981: 271 | P2981: 86 | Q2981: 4007792 | R2981: 750000 | S2981: =Q2981-R2981 -> 3257792 | T2981: =IF(R2981>0, (Q2981-R2981)/R2981, 0) -> 4.3437227 | U2981: =(N2981*4) + (T2981*0.4) + (M2981/10000) -> 32.837489 | V2981: =YEAR(B2981) -> 2012 | W2981: =TEXT(B2981, "mmmm") -> iyun | X2981: =TRIM(I2981) -> Colin Trevorrow | Y2981: =UPPER(A2981) -> SAFETY NOT GUARANTEED | Z2981: =IF(AND(R2981>50000000, S2981<0), "Underperformer", IF(AND(R2981<10000000, S2981>50000000), "Overperformer", "Normal")) -> Normal | AA2981: =VLOOKUP(D2981, lookups!$A$2:$B$18, 2, FALSE) -> Medium Budget | AB2981: =IF(AND(N2981>7, T2981>1, U2981>70), "Recommended", "Not Recommended") -> Not Recommended | AC2981: =IF(N2981>=8, "High Buzz / High Score", IF(AND(N2981<6, T2981<1), "High Buzz Mismatch", "Normal")) -> Normal
A2982: King's Ransom | B2982: 38495 | C2982: Color | D2982: Comedy | E2982: English | F2982: USA | G2982: PG-13 | H2982: Donald Faison | I2982: Jeffrey W. Byrd | J2982: 927 | K2982: 4990 | L2982: 2 | M2982: 83 | N2982: 4.1 | O2982: 23 | P2982: 95 | Q2982: 4006906 | R2982: 15000000 | S2982: =Q2982-R2982 -> -10993094 | T2982: =IF(R2982>0, (Q2982-R2982)/R2982, 0) -> -0.73287293 | U2982: =(N2982*4) + (T2982*0.4) + (M2982/10000) -> 16.115151 | V2982: =YEAR(B2982) -> 2005 | W2982: =TEXT(B2982, "mmmm") -> may | X2982: =TRIM(I2982) -> Jeffrey W. Byrd | Y2982: =UPPER(A2982) -> KİNG'S RANSOM | Z2982: =IF(AND(R2982>50000000, S2982<0), "Underperformer", IF(AND(R2982<10000000, S2982>50000000), "Overperformer", "Normal")) -> Normal | AA2982: =VLOOKUP(D2982, lookups!$A$2:$B$18, 2, FALSE) -> Medium Budget | AB2982: =IF(AND(N2982>7, T2982>1, U2982>70), "Recommended", "Not Recommended") -> Not Recommended | AC2982: =IF(N2982>=8, "High Buzz / High Score", IF(AND(N2982<6, T2982<1), "High Buzz Mismatch", "Normal")) -> High Buzz Mismatch
A2983: Idle Hands | B2983: 36476 | C2983: Color | D2983: Comedy | E2983: English | F2983: USA | G2983: R | H2983: Vivica A. Fox | I2983: Rodman Flender | J2983: 890 | K2983: 3654 | L2983: 6 | M2983: 0 | N2983: 6.2 | O2983: 59 | P2983: 92 | Q2983: 4002955 | R2983: 20000000 | S2983: =Q2983-R2983 -> -15997045 | T2983: =IF(R2983>0, (Q2983-R2983)/R2983, 0) -> -0.79985225 | U2983: =(N2983*4) + (T2983*0.4) + (M2983/10000) -> 24.480059 | V2983: =YEAR(B2983) -> 1999 | W2983: =TEXT(B2983, "mmmm") -> noyabr | X2983: =TRIM(I2983) -> Rodman Flender | Y2983: =UPPER(A2983) -> IDLE HANDS | Z2983: =IF(AND(R2983>50000000, S2983<0), "Underperformer", IF(AND(R2983<10000000, S2983>50000000), "Overperformer", "Normal")) -> Normal | AA2983: =VLOOKUP(D2983, lookups!$A$2:$B$18, 2, FALSE) -> Medium Budget | AB2983: =IF(AND(N2983>7, T2983>1, U2983>70), "Recommended", "Not Recommended") -> Not Recommended | AC2983: =IF(N2983>=8, "High Buzz / High Score", IF(AND(N2983<6, T2983<1), "High Buzz Mismatch", "Normal")) -> Normal
A2984: I'm Not There. | B2984: 39177 | C2984: Black and White | D2984: Biography | E2984: English | F2984: USA | G2984: R | H2984: Christian Bale | I2984: Todd Haynes | J2984: 23000 | K2984: 36398 | L2984: 162 | M2984: 0 | N2984: 7 | O2984: 231 | P2984: 135 | Q2984: 4001121 | R2984: 20000000 | S2984: =Q2984-R2984 -> -15998879 | T2984: =IF(R2984>0, (Q2984-R2984)/R2984, 0) -> -0.79994395 | U2984: =(N2984*4) + (T2984*0.4) + (M2984/10000) -> 27.680022 | V2984: =YEAR(B2984) -> 2007 | W2984: =TEXT(B2984, "mmmm") -> aprel | X2984: =TRIM(I2984) -> Todd Haynes | Y2984: =UPPER(A2984) -> I'M NOT THERE. | Z2984: =IF(AND(R2984>50000000, S2984<0), "Underperformer", IF(AND(R2984<10000000, S2984>50000000), "Overperformer", "Normal")) -> Normal | AA2984: =VLOOKUP(D2984, lookups!$A$2:$B$18, 2, FALSE) -> Medium Budget | AB2984: =IF(AND(N2984>7, T2984>1, U2984>70), "Recommended", "Not Recommended") -> Not Recommended | AC2984: =IF(N2984>=8, "High Buzz / High Score", IF(AND(N2984<6, T2984<1), "High Buzz Mismatch", "Normal")) -> Normal
A2985: Shame | B2985: 40877 | C2985: Color | D2985: Drama | E2985: English | F2985: UK | G2985: NC-17 | H2985: Michael Fassbender | I2985: Steve McQueen | J2985: 13000 | K2985: 15230 | L2985: 0 | M2985: 23000 | N2985: 7.3 | O2985: 486 | P2985: 101 | Q2985: 4000304 | R2985: 6500000 | S2985: =Q2985-R2985 -> -2499696 | T2985: =IF(R2985>0, (Q2985-R2985)/R2985, 0) -> -0.38456862 | U2985: =(N2985*4) + (T2985*0.4) + (M2985/10000) -> 31.346173 | V2985: =YEAR(B2985) -> 2011 | W2985: =TEXT(B2985, "mmmm") -> noyabr | X2985: =TRIM(I2985) -> Steve McQueen | Y2985: =UPPER(A2985) -> SHAME | Z2985: =IF(AND(R2985>50000000, S2985<0), "Underperformer", IF(AND(R2985<10000000, S2985>50000000), "Overperformer", "Normal")) -> Normal | AA2985: =VLOOKUP(D2985, lookups!$A$2:$B$18, 2, FALSE) -> Medium Budget | AB2985: =IF(AND(N2985>7, T2985>1, U2985>70), "Recommended", "Not Recommended") -> Not Recommended | AC2985: =IF(N2985>=8, "High Buzz / High Score", IF(AND(N2985<6, T2985<1), "High Buzz Mismatch", "Normal")) -> Normal
A2986: American Ninja 2: The Confrontation | B2986: 31944 | C2986: Color | D2986: Action | E2986: English | F2986: USA | G2986: R | H2986: Michael Dudikoff | I2986: Sam Firstenberg | J2986: 615 | K2986: 872 | L2986: 44 | M2986: 583 | N2986: 4.7 | O2986: 40 | P2986: 90 | Q2986: 4000000 | R2986: 350000 | S2986: =Q2986-R2986 -> 3650000 | T2986: =IF(R2986>0, (Q2986-R2986)/R2986, 0) -> 10.428571 | U2986: =(N2986*4) + (T2986*0.4) + (M2986/10000) -> 23.029729 | V2986: =YEAR(B2986) -> 1987 | W2986: =TEXT(B2986, "mmmm") -> iyun | X2986: =TRIM(I2986) -> Sam Firstenberg | Y2986: =UPPER(A2986) -> AMERİCAN NİNJA 2: THE CONFRONTATİON | Z2986: =IF(AND(R2986>50000000, S2986<0), "Underperformer", IF(AND(R2986<10000000, S2986>50000000), "Overperformer", "Normal")) -> Normal | AA2986: =VLOOKUP(D2986, lookups!$A$2:$B$18, 2, FALSE) -> High Budget | AB2986: =IF(AND(N2986>7, T2986>1, U2986>70), "Recommended", "Not Recommended") -> Not Recommended | AC2986: =IF(N2986>=8, "High Buzz / High Score", IF(AND(N2986<6, T2986<1), "High Buzz Mismatch", "Normal")) -> Normal
... A3062: Top Hat | B3062: 12889 | C3062: Black and White | D3062: Comedy | E3062: English | F3062: USA | G3062: Approved | H3062: Ginger Rogers | I3062: Mark Sandrich | J3062: 610 | K3062: 824 | L3062: 10 | M3062: 1000 | N3062: 7.8 | O3062: 66 | P3062: 81 | Q3062: 3000000 | R3062: 609000 | S3062: =Q3062-R3062 -> 2391000 | T3062: =IF(R3062>0, (Q3062-R3062)/R3062, 0) -> 3.9261084 | U3062: =(N3062*4) + (T3062*0.4) + (M3062/10000) -> 32.870443 | V3062: =YEAR(B3062) -> 1935 | W3062: =TEXT(B3062, "mmmm") -> aprel | X3062: =TRIM(I3062) -> Mark Sandrich | Y3062: =UPPER(A3062) -> TOP HAT | Z3062: =IF(AND(R3062>50000000, S3062<0), "Underperformer", IF(AND(R3062<10000000, S3062>50000000), "Overperformer", "Normal")) -> Normal | AA3062: =VLOOKUP(D3062, lookups!$A$2:$B$18, 2, FALSE) -> Medium Budget | AB3062: =IF(AND(N3062>7, T3062>1, U3062>70), "Recommended", "Not Recommended") -> Not Recommended | AC3062: =IF(N3062>=8, "High Buzz / High Score", IF(AND(N3062<6, T3062<1), "High Buzz Mismatch", "Normal")) -> Normal
A3063: Happiness | B3063: 35869 | C3063: Color | D3063: Comedy | E3063: English | F3063: USA | H3063: Philip Seymour Hoffman | I3063: Todd Solondz | J3063: 22000 | K3063: 36859 | L3063: 377 | M3063: 0 | N3063: 7.8 | O3063: 148 | P3063: 134 | Q3063: 3000000 | R3063: 3000000 | S3063: =Q3063-R3063 -> 0 | T3063: =IF(R3063>0, (Q3063-R3063)/R3063, 0) -> 0 | U3063: =(N3063*4) + (T3063*0.4) + (M3063/10000) -> 31.2 | V3063: =YEAR(B3063) -> 1998 | W3063: =TEXT(B3063, "mmmm") -> mart | X3063: =TRIM(I3063) -> Todd Solondz | Y3063: =UPPER(A3063) -> HAPPİNESS | Z3063: =IF(AND(R3063>50000000, S3063<0), "Underperformer", IF(AND(R3063<10000000, S3063>50000000), "Overperformer", "Normal")) -> Normal | AA3063: =VLOOKUP(D3063, lookups!$A$2:$B$18, 2, FALSE) -> Medium Budget | AB3063: =IF(AND(N3063>7, T3063>1, U3063>70), "Recommended", "Not Recommended") -> Not Recommended | AC3063: =IF(N3063>=8, "High Buzz / High Score", IF(AND(N3063<6, T3063<1), "High Buzz Mismatch", "Normal")) -> Normal
A3064: Miss Potter | B3064: 38745 | C3064: Color | D3064: Biography | E3064: English | F3064: UK | G3064: PG | H3064: Emily Watson | I3064: Chris Noonan | J3064: 876 | K3064: 1518 | L3064: 108 | M3064: 0 | N3064: 7 | O3064: 124 | P3064: 88 | Q3064: 2975649 | R3064: 30000000 | S3064: =Q3064-R3064 -> -27024351 | T3064: =IF(R3064>0, (Q3064-R3064)/R3064, 0) -> -0.9008117 | U3064: =(N3064*4) + (T3064*0.4) + (M3064/10000) -> 27.639675 | V3064: =YEAR(B3064) -> 2006 | W3064: =TEXT(B3064, "mmmm") -> yanvar | X3064: =TRIM(I3064) -> Chris Noonan | Y3064: =UPPER(A3064) -> MİSS POTTER | Z3064: =IF(AND(R3064>50000000, S3064<0), "Underperformer", IF(AND(R3064<10000000, S3064>50000000), "Overperformer", "Normal")) -> Normal | AA3064: =VLOOKUP(D3064, lookups!$A$2:$B$18, 2, FALSE) -> Medium Budget | AB3064: =IF(AND(N3064>7, T3064>1, U3064>70), "Recommended", "Not Recommended") -> Not Recommended | AC3064: =IF(N3064>=8, "High Buzz / High Score", IF(AND(N3064<6, T3064<1), "High Buzz Mismatch", "Normal")) -> Normal
A3065: Before I Go to Sleep | B3065: 41702 | C3065: Color | D3065: Drama | E3065: English | F3065: UK | G3065: R | H3065: Colin Firth | I3065: Rowan Joffe | J3065: 14000 | K3065: 14617 | L3065: 17 | M3065: 11000 | N3065: 6.3 | O3065: 149 | P3065: 92 | Q3065: 2963012 | R3065: 22000000 | S3065: =Q3065-R3065 -> -19036988 | T3065: =IF(R3065>0, (Q3065-R3065)/R3065, 0) -> -0.86531764 | U3065: =(N3065*4) + (T3065*0.4) + (M3065/10000) -> 25.953873 | V3065: =YEAR(B3065) -> 2014 | W3065: =TEXT(B3065, "mmmm") -> mart | X3065: =TRIM(I3065) -> Rowan Joffe | Y3065: =UPPER(A3065) -> BEFORE I GO TO SLEEP | Z3065: =IF(AND(R3065>50000000, S3065<0), "Underperformer", IF(AND(R3065<10000000, S3065>50000000), "Overperformer", "Normal")) -> Normal | AA3065: =VLOOKUP(D3065, lookups!$A$2:$B$18, 2, FALSE) -> Medium Budget | AB3065: =IF(AND(N3065>7, T3065>1, U3065>70), "Recommended", "Not Recommended") -> Not Recommended | AC3065: =IF(N3065>=8, "High Buzz / High Score", IF(AND(N3065<6, T3065<1), "High Buzz Mismatch", "Normal")) -> Normal
A3066: Basquiat | B3066: 35390 | C3066: Color | D3066: Biography | E3066: English | F3066: USA | G3066: R | H3066: Gary Oldman | I3066: Julian Schnabel | J3066: 10000 | K3066: 11459 | L3066: 232 | M3066: 0 | N3066: 6.9 | O3066: 42 | P3066: 108 | Q3066: 2961991 | R3066: 3300000 | S3066: =Q3066-R3066 -> -338009 | T3066: =IF(R3066>0, (Q3066-R3066)/R3066, 0) -> -0.10242697 | U3066: =(N3066*4) + (T3066*0.4) + (M3066/10000) -> 27.559029 | V3066: =YEAR(B3066) -> 1996 | W3066: =TEXT(B3066, "mmmm") -> noyabr | X3066: =TRIM(I3066) -> Julian Schnabel | Y3066: =UPPER(A3066) -> BASQUİAT | Z3066: =IF(AND(R3066>50000000, S3066<0), "Underperformer", IF(AND(R3066<10000000, S3066>50000000), "Overperformer", "Normal")) -> Normal | AA3066: =VLOOKUP(D3066, lookups!$A$2:$B$18, 2, FALSE) -> Medium Budget | AB3066: =IF(AND(N3066>7, T3066>1, U3066>70), "Recommended", "Not Recommended") -> Not Recommended | AC3066: =IF(N3066>=8, "High Buzz / High Score", IF(AND(N3066<6, T3066<1), "High Buzz Mismatch", "Normal")) -> Normal
A3067: Man on Wire | B3067: 39762 | C3067: Color | D3067: Biography | E3067: English | F3067: UK | G3067: PG-13 | H3067: Paul McGill | I3067: James Marsh | J3067: 41 | K3067: 68 | L3067: 120 | M3067: 0 | N3067: 7.8 | O3067: 194 | P3067: 90 | Q3067: 2957978 | R3067: 1000000 | S3067: =Q3067-R3067 -> 1957978 | T3067: =IF(R3067>0, (Q3067-R3067)/R3067, 0) -> 1.957978 | U3067: =(N3067*4) + (T3067*0.4) + (M3067/10000) -> 31.983191 | V3067: =YEAR(B3067) -> 2008 | W3067: =TEXT(B3067, "mmmm") -> noyabr | X3067: =TRIM(I3067) -> James Marsh | Y3067: =UPPER(A3067) -> MAN ON WİRE | Z3067: =IF(AND(R3067>50000000, S3067<0), "Underperformer", IF(AND(R3067<10000000, S3067>50000000), "Overperformer", "Normal")) -> Normal | AA3067: =VLOOKUP(D3067, lookups!$A$2:$B$18, 2, FALSE) -> Medium Budget | AB3067: =IF(AND(N3067>7, T3067>1, U3067>70), "Recommended", "Not Recommended") -> Not Recommended | AC3067: =IF(N3067>=8, "High Buzz / High Score", IF(AND(N3067<6, T3067<1), "High Buzz Mismatch", "Normal")) -> Normal
A3068: The Pirate | B3068: 17630 | C3068: Color | D3068: Adventure | E3068: English | F3068: USA | G3068: Approved | H3068: Gladys Cooper | I3068: Vincente Minnelli | J3068: 89 | K3068: 282 | L3068: 136 | M3068: 359 | N3068: 7.1 | O3068: 41 | P3068: 102 | Q3068: 2956000 | R3068: 3700000 | S3068: =Q3068-R3068 -> -744000 | T3068: =IF(R3068>0, (Q3068-R3068)/R3068, 0) -> -0.20108108 | U3068: =(N3068*4) + (T3068*0.4) + (M3068/10000) -> 28.355468 | V3068: =YEAR(B3068) -> 1948 | W3068: =TEXT(B3068, "mmmm") -> aprel | X3068: =TRIM(I3068) -> Vincente Minnelli | Y3068: =UPPER(A3068) -> THE PİRATE | Z3068: =IF(AND(R3068>50000000, S3068<0), "Underperformer", IF(AND(R3068<10000000, S3068>50000000), "Overperformer", "Normal")) -> Normal | AA3068: =VLOOKUP(D3068, lookups!$A$2:$B$18, 2, FALSE) -> High Budget | AB3068: =IF(AND(N3068>7, T3068>1, U3068>70), "Recommended", "Not Recommended") -> Not Recommended | AC3068: =IF(N3068>=8, "High Buzz / High Score", IF(AND(N3068<6, T3068<1), "High Buzz Mismatch", "Normal")) -> Normal
A3069: Gracie | B3069: 39086 | C3069: Color | D3069: Biography | E3069: English | F3069: USA | G3069: PG-13 | H3069: Emma Bell | I3069: Davis Guggenheim | J3069: 702 | K3069: 2007 | L3069: 49 | M3069: 313 | N3069: 6.2 | O3069: 65 | P3069: 95 | Q3069: 2955039 | R3069: 9000000 | S3069: =Q3069-R3069 -> -6044961 | T3069: =IF(R3069>0, (Q3069-R3069)/R3069, 0) -> -0.67166233 | U3069: =(N3069*4) + (T3069*0.4) + (M3069/10000) -> 24.562635 | V3069: =YEAR(B3069) -> 2007 | W3069: =TEXT(B3069, "mmmm") -> yanvar | X3069: =TRIM(I3069) -> Davis Guggenheim | Y3069: =UPPER(A3069) -> GRACİE | Z3069: =IF(AND(R3069>50000000, S3069<0), "Underperformer", IF(AND(R3069<10000000, S3069>50000000), "Overperformer", "Normal")) -> Normal | AA3069: =VLOOKUP(D3069, lookups!$A$2:$B$18, 2, FALSE) -> Medium Budget | AB3069: =IF(AND(N3069>7, T3069>1, U3069>70), "Recommended", "Not Recommended") -> Not Recommended | AC3069: =IF(N3069>=8, "High Buzz / High Score", IF(AND(N3069<6, T3069<1), "High Buzz Mismatch", "Normal")) -> Normal
A3070: Isn't She Great | B3070: 36734 | C3070: Color | D3070: Biography | E3070: English | F3070: USA | G3070: R | H3070: Stockard Channing | I3070: Andrew Bergman | J3070: 944 | K3070: 2928 | L3070: 31 | M3070: 133 | N3070: 5.3 | O3070: 63 | P3070: 95 | Q3070: 2954405 | R3070: 36000000 | S3070: =Q3070-R3070 -> -33045595 | T3070: =IF(R3070>0, (Q3070-R3070)/R3070, 0) -> -0.91793319 | U3070: =(N3070*4) + (T3070*0.4) + (M3070/10000) -> 20.846127 | V3070: =YEAR(B3070) -> 2000 | W3070: =TEXT(B3070, "mmmm") -> iyul | X3070: =TRIM(I3070) -> Andrew Bergman | Y3070: =UPPER(A3070) -> ISN'T SHE GREAT | Z3070: =IF(AND(R3070>50000000, S3070<0), "Underperformer", IF(AND(R3070<10000000, S3070>50000000), "Overperformer", "Normal")) -> Normal | AA3070: =VLOOKUP(D3070, lookups!$A$2:$B$18, 2, FALSE) -> Medium Budget | AB3070: =IF(AND(N3070>7, T3070>1, U3070>70), "Recommended", "Not Recommended") -> Not Recommended | AC3070: =IF(N3070>=8, "High Buzz / High Score", IF(AND(N3070<6, T3070<1), "High Buzz Mismatch", "Normal")) -> High Buzz Mismatch
A3071: Metropolitan | B3071: 32910 | C3071: Color | D3071: Comedy | E3071: English | F3071: USA | G3071: PG-13 | H3071: Chris Eigeman | I3071: Whit Stillman | J3071: 88 | K3071: 173 | L3071: 89 | M3071: 865 | N3071: 7.5 | O3071: 71 | P3071: 98 | Q3071: 2938208 | R3071: 225000 | S3071: =Q3071-R3071 -> 2713208 | T3071: =IF(R3071>0, (Q3071-R3071)/R3071, 0) -> 12.058702 | U3071: =(N3071*4) + (T3071*0.4) + (M3071/10000) -> 34.909981 | V3071: =YEAR(B3071) -> 1990 | W3071: =TEXT(B3071, "mmmm") -> fevral | X3071: =TRIM(I3071) -> Whit Stillman | Y3071: =UPPER(A3071) -> METROPOLİTAN | Z3071: =IF(AND(R3071>50000000, S3071<0), "Underperformer", IF(AND(R3071<10000000, S3071>50000000), "Overperformer", "Normal")) -> Normal | AA3071: =VLOOKUP(D3071, lookups!$A$2:$B$18, 2, FALSE) -> Medium Budget | AB3071: =IF(AND(N3071>7, T3071>1, U3071>70), "Recommended", "Not Recommended") -> Not Recommended | AC3071: =IF(N3071>=8, "High Buzz / High Score", IF(AND(N3071<6, T3071<1), "High Buzz Mismatch", "Normal")) -> Normal
A3072: Choke | B3072: 39715 | C3072: Color | D3072: Comedy | E3072: English | F3072: USA | G3072: R | H3072: Anjelica Huston | I3072: Clark Gregg | J3072: 1000 | K3072: 3608 | L3072: 0 | M3072: 0 | N3072: 6.5 | O3072: 159 | P3072: 92 | Q3072: 2926565 | R3072: 3000000 | S3072: =Q3072-R3072 -> -73435 | T3072: =IF(R3072>0, (Q3072-R3072)/R3072, 0) -> -0.024478333 | U3072: =(N3072*4) + (T3072*0.4) + (M3072/10000) -> 25.990209 | V3072: =YEAR(B3072) -> 2008 | W3072: =TEXT(B3072, "mmmm") -> sentyabr | X3072: =TRIM(I3072) -> Clark Gregg | Y3072: =UPPER(A3072) -> CHOKE | Z3072: =IF(AND(R3072>50000000, S3072<0), "Underperformer", IF(AND(R3072<10000000, S3072>50000000), "Overperformer", "Normal")) -> Normal | AA3072: =VLOOKUP(D3072, lookups!$A$2:$B$18, 2, FALSE) -> Medium Budget | AB3072: =IF(AND(N3072>7, T3072>1, U3072>70), "Recommended", "Not Recommended") -> Not Recommended | AC3072: =IF(N3072>=8, "High Buzz / High Score", IF(AND(N3072<6, T3072<1), "High Buzz Mismatch", "Normal")) -> Normal
A3073: Veer-Zaara | B3073: 38180 | C3073: Color | D3073: Drama | E3073: Hindi | F3073: India | H3073: Shah Rukh Khan | I3073: Yash Chopra | J3073: 8000 | K3073: 9984 | L3073: 147 | M3073: 2000 | N3073: 7.9 | O3073: 29 | P3073: 192 | Q3073: 2921738 | R3073: 7000000 | S3073: =Q3073-R3073 -> -4078262 | T3073: =IF(R3073>0, (Q3073-R3073)/R3073, 0) -> -0.58260886 | U3073: =(N3073*4) + (T3073*0.4) + (M3073/10000) -> 31.566956 | V3073: =YEAR(B3073) -> 2004 | W3073: =TEXT(B3073, "mmmm") -> iyul | X3073: =TRIM(I3073) -> Yash Chopra | Y3073: =UPPER(A3073) -> VEER-ZAARA | Z3073: =IF(AND(R3073>50000000, S3073<0), "Underperformer", IF(AND(R3073<10000000, S3073>50000000), "Overperformer", "Normal")) -> Normal | AA3073: =VLOOKUP(D3073, lookups!$A$2:$B$18, 2, FALSE) -> Medium Budget | AB3073: =IF(AND(N3073>7, T3073>1, U3073>70), "Recommended", "Not Recommended") -> Not Recommended | AC3073: =IF(N3073>=8, "High Buzz / High Score", IF(AND(N3073<6, T3073<1), "High Buzz Mismatch", "Normal")) -> Normal
A3074: Tsotsi | B3074: 38688 | C3074: Color | D3074: Crime | E3074: Zulu | F3074: UK | G3074: R | H3074: Terry Pheto | I3074: Gavin Hood | J3074: 113 | K3074: 278 | L3074: 151 | M3074: 0 | N3074: 7.3 | O3074: 152 | P3074: 94 | Q3074: 2912363 | R3074: 3000000 | S3074: =Q3074-R3074 -> -87637 | T3074: =IF(R3074>0, (Q3074-R3074)/R3074, 0) -> -0.029212333 | U3074: =(N3074*4) + (T3074*0.4) + (M3074/10000) -> 29.188315 | V3074: =YEAR(B3074) -> 2005 | W3074: =TEXT(B3074, "mmmm") -> dekabr | X3074: =TRIM(I3074) -> Gavin Hood | Y3074: =UPPER(A3074) -> TSOTSİ | Z3074: =IF(AND(R3074>50000000, S3074<0), "Underperformer", IF(AND(R3074<10000000, S3074>50000000), "Overperformer", "Normal")) -> Normal | AA3074: =VLOOKUP(D3074, lookups!$A$2:$B$18, 2, FALSE) -> Medium Budget | AB3074: =IF(AND(N3074>7, T3074>1, U3074>70), "Recommended", "Not Recommended") -> Not Recommended | AC3074: =IF(N3074>=8, "High Buzz / High Score", IF(AND(N3074<6, T3074<1), "High Buzz Mismatch", "Normal")) -> Normal
A3075: Cradle Will Rock | B3075: 36504 | C3075: Color | D3075: Drama | E3075: English | F3075: USA | G3075: R | H3075: Bill Murray | I3075: Tim Robbins | J3075: 13000 | K3075: 16878 | L3075: 0 | M3075: 625 | N3075: 6.9 | O3075: 70 | P3075: 132 | Q3075: 2899970 | R3075: 32000000 | S3075: =Q3075-R3075 -> -29100030 | T3075: =IF(R3075>0, (Q3075-R3075)/R3075, 0) -> -0.90937594 | U3075: =(N3075*4) + (T3075*0.4) + (M3075/10000) -> 27.29875 | V3075: =YEAR(B3075) -> 1999 | W3075: =TEXT(B3075, "mmmm") -> dekabr | X3075: =TRIM(I3075) -> Tim Robbins | Y3075: =UPPER(A3075) -> CRADLE WİLL ROCK | Z3075: =IF(AND(R3075>50000000, S3075<0), "Underperformer", IF(AND(R3075<10000000, S3075>50000000), "Overperformer", "Normal")) -> Normal | AA3075: =VLOOKUP(D3075, lookups!$A$2:$B$18, 2, FALSE) -> Medium Budget | AB3075: =IF(AND(N3075>7, T3075>1, U3075>70), "Recommended", "Not Recommended") -> Not Recommended | AC3075: =IF(N3075>=8, "High Buzz / High Score", IF(AND(N3075<6, T3075<1), "High Buzz Mismatch", "Normal")) -> Normal
A3076: Waiting for Guffman | B3076: 35428 | C3076: Color | D3076: Comedy | E3076: English | F3076: USA | G3076: R | H3076: Catherine O'Hara | I3076: Christopher Guest | J3076: 925 | K3076: 3559 | L3076: 378 | M3076: 0 | N3076: 7.6 | O3076: 50 | P3076: 84 | Q3076: 2892582 | R3076: 4000000 | S3076: =Q3076-R3076 -> -1107418 | T3076: =IF(R3076>0, (Q3076-R3076)/R3076, 0) -> -0.2768545 | U3076: =(N3076*4) + (T3076*0.4) + (M3076/10000) -> 30.289258 | V3076: =YEAR(B3076) -> 1996 | W3076: =TEXT(B3076, "mmmm") -> dekabr | X3076: =TRIM(I3076) -> Christopher Guest | Y3076: =UPPER(A3076) -> WAİTİNG FOR GUFFMAN | Z3076: =IF(AND(R3076>50000000, S3076<0), "Underperformer", IF(AND(R3076<10000000, S3076>50000000), "Overperformer", "Normal")) -> Normal | AA3076: =VLOOKUP(D3076, lookups!$A$2:$B$18, 2, FALSE) -> Medium Budget | AB3076: =IF(AND(N3076>7, T3076>1, U3076>70), "Recommended", "Not Recommended") -> Not Recommended | AC3076: =IF(N3076>=8, "High Buzz / High Score", IF(AND(N3076<6, T3076<1), "High Buzz Mismatch", "Normal")) -> Normal
A3077: Tadpole | B3077: 36841 | C3077: Color | D3077: Comedy | E3077: English | F3077: USA | G3077: PG-13 | H3077: Bebe Neuwirth | I3077: Gary Winick | J3077: 376 | K3077: 1144 | L3077: 56 | M3077: 132 | N3077: 6.3 | O3077: 91 | P3077: 78 | Q3077: 2882062 | R3077: 150000 | S3077: =Q3077-R3077 -> 2732062 | T3077: =IF(R3077>0, (Q3077-R3077)/R3077, 0) -> 18.213747 | U3077: =(N3077*4) + (T3077*0.4) + (M3077/10000) -> 32.498699 | V3077: =YEAR(B3077) -> 2000 | W3077: =TEXT(B3077, "mmmm") -> noyabr | X3077: =TRIM(I3077) -> Gary Winick | Y3077: =UPPER(A3077) -> TADPOLE | Z3077: =IF(AND(R3077>50000000, S3077<0), "Underperformer", IF(AND(R3077<10000000, S3077>50000000), "Overperformer", "Normal")) -> Normal | AA3077: =VLOOKUP(D3077, lookups!$A$2:$B$18, 2, FALSE) -> Medium Budget | AB3077: =IF(AND(N3077>7, T3077>1, U3077>70), "Recommended", "Not Recommended") -> Not Recommended | AC3077: =IF(N3077>=8, "High Buzz / High Score", IF(AND(N3077<6, T3077<1), "High Buzz Mismatch", "Normal")) -> Normal
A3078: The Hudsucker Proxy | B3078: 34504 | C3078: Black and White | D3078: Comedy | E3078: English | F3078: UK | G3078: PG | H3078: Jennifer Jason Leigh | I3078: Joel Coen | J3078: 1000 | K3078: 2612 | L3078: 0 | M3078: 0 | N3078: 7.3 | O3078: 77 | P3078: 111 | Q3078: 2869369 | R3078: 30000000 | S3078: =Q3078-R3078 -> -27130631 | T3078: =IF(R3078>0, (Q3078-R3078)/R3078, 0) -> -0.90435437 | U3078: =(N3078*4) + (T3078*0.4) + (M3078/10000) -> 28.838258 | V3078: =YEAR(B3078) -> 1994 | W3078: =TEXT(B3078, "mmmm") -> iyun | X3078: =TRIM(I3078) -> Joel Coen | Y3078: =UPPER(A3078) -> THE HUDSUCKER PROXY | Z3078: =IF(AND(R3078>50000000, S3078<0), "Underperformer", IF(AND(R3078<10000000, S3078>50000000), "Overperformer", "Normal")) -> Normal | AA3078: =VLOOKUP(D3078, lookups!$A$2:$B$18, 2, FALSE) -> Medium Budget | AB3078: =IF(AND(N3078>7, T3078>1, U3078>70), "Recommended", "Not Recommended") -> Not Recommended | AC3078: =IF(N3078>=8, "High Buzz / High Score", IF(AND(N3078<6, T3078<1), "High Buzz Mismatch", "Normal")) -> Normal
A3079: Home Run | B3079: 41532 | C3079: Color | D3079: Drama | E3079: English | F3079: USA | G3079: PG-13 | H3079: Vivica A. Fox | I3079: David Boyd | J3079: 890 | K3079: 2681 | L3079: 29 | M3079: 0 | N3079: 6 | O3079: 10 | P3079: 113 | Q3079: 2859955 | R3079: 1200000 | S3079: =Q3079-R3079 -> 1659955 | T3079: =IF(R3079>0, (Q3079-R3079)/R3079, 0) -> 1.3832958 | U3079: =(N3079*4) + (T3079*0.4) + (M3079/10000) -> 24.553318 | V3079: =YEAR(B3079) -> 2013 | W3079: =TEXT(B3079, "mmmm") -> sentyabr | X3079: =TRIM(I3079) -> David Boyd | Y3079: =UPPER(A3079) -> HOME RUN | Z3079: =IF(AND(R3079>50000000, S3079<0), "Underperformer", IF(AND(R3079<10000000, S3079>50000000), "Overperformer", "Normal")) -> Normal | AA3079: =VLOOKUP(D3079, lookups!$A$2:$B$18, 2, FALSE) -> Medium Budget | AB3079: =IF(AND(N3079>7, T3079>1, U3079>70), "Recommended", "Not Recommended") -> Not Recommended | AC3079: =IF(N3079>=8, "High Buzz / High Score", IF(AND(N3079<6, T3079<1), "High Buzz Mismatch", "Normal")) -> Normal
A3080: In the Company of Men | B3080: 35448 | C3080: Color | D3080: Comedy | E3080: English | F3080: Canada | G3080: R | H3080: Stacy Edwards | I3080: Neil LaBute | J3080: 136 | K3080: 254 | L3080: 119 | M3080: 489 | N3080: 7.3 | O3080: 80 | P3080: 97 | Q3080: 2856622 | R3080: 25000 | S3080: =Q3080-R3080 -> 2831622 | T3080: =IF(R3080>0, (Q3080-R3080)/R3080, 0) -> 113.26488 | U3080: =(N3080*4) + (T3080*0.4) + (M3080/10000) -> 74.554852 | V3080: =YEAR(B3080) -> 1997 | W3080: =TEXT(B3080, "mmmm") -> yanvar | X3080: =TRIM(I3080) -> Neil LaBute | Y3080: =UPPER(A3080) -> IN THE COMPANY OF MEN | Z3080: =IF(AND(R3080>50000000, S3080<0), "Underperformer", IF(AND(R3080<10000000, S3080>50000000), "Overperformer", "Normal")) -> Normal | AA3080: =VLOOKUP(D3080, lookups!$A$2:$B$18, 2, FALSE) -> Medium Budget | AB3080: =IF(AND(N3080>7, T3080>1, U3080>70), "Recommended", "Not Recommended") -> Recommended | AC3080: =IF(N3080>=8, "High Buzz / High Score", IF(AND(N3080<6, T3080<1), "High Buzz Mismatch", "Normal")) -> Normal
A3081: Airborne | B3081: 34221 | C3081: Color | D3081: Adventure | E3081: English | F3081: USA | G3081: PG | H3081: Alanna Ubach | I3081: Rob Bowman | J3081: 584 | K3081: 1218 | L3081: 38 | M3081: 0 | N3081: 6.2 | O3081: 9 | P3081: 91 | Q3081: 2850263 | R3081: 2600000 | S3081: =Q3081-R3081 -> 250263 | T3081: =IF(R3081>0, (Q3081-R3081)/R3081, 0) -> 0.096255 | U3081: =(N3081*4) + (T3081*0.4) + (M3081/10000) -> 24.838502 | V3081: =YEAR(B3081) -> 1993 | W3081: =TEXT(B3081, "mmmm") -> sentyabr | X3081: =TRIM(I3081) -> Rob Bowman | Y3081: =UPPER(A3081) -> AİRBORNE | Z3081: =IF(AND(R3081>50000000, S3081<0), "Underperformer", IF(AND(R3081<10000000, S3081>50000000), "Overperformer", "Normal")) -> Normal | AA3081: =VLOOKUP(D3081, lookups!$A$2:$B$18, 2, FALSE) -> High Budget | AB3081: =IF(AND(N3081>7, T3081>1, U3081>70), "Recommended", "Not Recommended") -> Not Recommended | AC3081: =IF(N3081>=8, "High Buzz / High Score", IF(AND(N3081<6, T3081<1), "High Buzz Mismatch", "Normal")) -> Normal
A3082: Things We Lost in the Fire | B3082: 39149 | C3082: Color | D3082: Drama | E3082: English | F3082: USA | G3082: R | H3082: Alison Lohman | I3082: Susanne Bier | J3082: 1000 | K3082: 1889 | L3082: 369 | M3082: 0 | N3082: 7.2 | O3082: 146 | P3082: 118 | Q3082: 2849142 | R3082: 16000000 | S3082: =Q3082-R3082 -> -13150858 | T3082: =IF(R3082>0, (Q3082-R3082)/R3082, 0) -> -0.82192862 | U3082: =(N3082*4) + (T3082*0.4) + (M3082/10000) -> 28.471229 | V3082: =YEAR(B3082) -> 2007 | W3082: =TEXT(B3082, "mmmm") -> mart | X3082: =TRIM(I3082) -> Susanne Bier | Y3082: =UPPER(A3082) -> THİNGS WE LOST İN THE FİRE | Z3082: =IF(AND(R3082>50000000, S3082<0), "Underperformer", IF(AND(R3082<10000000, S3082>50000000), "Overperformer", "Normal")) -> Normal | AA3082: =VLOOKUP(D3082, lookups!$A$2:$B$18, 2, FALSE) -> Medium Budget | AB3082: =IF(AND(N3082>7, T3082>1, U3082>70), "Recommended", "Not Recommended") -> Not Recommended | AC3082: =IF(N3082>=8, "High Buzz / High Score", IF(AND(N3082<6, T3082<1), "High Buzz Mismatch", "Normal")) -> Normal
A3083: Letters to God | B3083: 40511 | C3083: Color | D3083: Drama | E3083: English | F3083: USA | G3083: PG | H3083: Robyn Lively | I3083: David Nixon | J3083: 439 | K3083: 1567 | L3083: 13 | M3083: 0 | N3083: 6.3 | O3083: 19 | P3083: 110 | Q3083: 2848578 | R3083: 3500000 | S3083: =Q3083-R3083 -> -651422 | T3083: =IF(R3083>0, (Q3083-R3083)/R3083, 0) -> -0.18612057 | U3083: =(N3083*4) + (T3083*0.4) + (M3083/10000) -> 25.125552 | V3083: =YEAR(B3083) -> 2010 | W3083: =TEXT(B3083, "mmmm") -> noyabr | X3083: =TRIM(I3083) -> David Nixon | Y3083: =UPPER(A3083) -> LETTERS TO GOD | Z3083: =IF(AND(R3083>50000000, S3083<0), "Underperformer", IF(AND(R3083<10000000, S3083>50000000), "Overperformer", "Normal")) -> Normal | AA3083: =VLOOKUP(D3083, lookups!$A$2:$B$18, 2, FALSE) -> Medium Budget | AB3083: =IF(AND(N3083>7, T3083>1, U3083>70), "Recommended", "Not Recommended") -> Not Recommended | AC3083: =IF(N3083>=8, "High Buzz / High Score", IF(AND(N3083<6, T3083<1), "High Buzz Mismatch", "Normal")) -> Normal
A3084: eXistenZ | B3084: 36172 | C3084: Color | D3084: Horror | E3084: English | F3084: Canada | G3084: R | H3084: Jennifer Jason Leigh | I3084: David Cronenberg | J3084: 1000 | K3084: 2990 | L3084: 0 | M3084: 6000 | N3084: 6.8 | O3084: 196 | P3084: 115 | Q3084: 2840417 | R3084: 31000000 | S3084: =Q3084-R3084 -> -28159583 | T3084: =IF(R3084>0, (Q3084-R3084)/R3084, 0) -> -0.90837365 | U3084: =(N3084*4) + (T3084*0.4) + (M3084/10000) -> 27.436651 | V3084: =YEAR(B3084) -> 1999 | W3084: =TEXT(B3084, "mmmm") -> yanvar | X3084: =TRIM(I3084) -> David Cronenberg | Y3084: =UPPER(A3084) -> EXİSTENZ | Z3084: =IF(AND(R3084>50000000, S3084<0), "Underperformer", IF(AND(R3084<10000000, S3084>50000000), "Overperformer", "Normal")) -> Normal | AA3084: =VLOOKUP(D3084, lookups!$A$2:$B$18, 2, FALSE) -> Low Budget | AB3084: =IF(AND(N3084>7, T3084>1, U3084>70), "Recommended", "Not Recommended") -> Not Recommended | AC3084: =IF(N3084>=8, "High Buzz / High Score", IF(AND(N3084<6, T3084<1), "High Buzz Mismatch", "Normal")) -> Normal
A3085: The Great Beauty | B3085: 41279 | C3085: Color | D3085: Drama | E3085: Italian | F3085: Italy | G3085: Not Rated | H3085: Toni Servillo | I3085: Paolo Sorrentino | J3085: 211 | K3085: 456 | L3085: 667 | M3085: 29000 | N3085: 7.7 | O3085: 280 | P3085: 172 | Q3085: 2835886 | R3085: 9200000 | S3085: =Q3085-R3085 -> -6364114 | T3085: =IF(R3085>0, (Q3085-R3085)/R3085, 0) -> -0.69175152 | U3085: =(N3085*4) + (T3085*0.4) + (M3085/10000) -> 33.423299 | V3085: =YEAR(B3085) -> 2013 | W3085: =TEXT(B3085, "mmmm") -> yanvar | X3085: =TRIM(I3085) -> Paolo Sorrentino | Y3085: =UPPER(A3085) -> THE GREAT BEAUTY | Z3085: =IF(AND(R3085>50000000, S3085<0), "Underperformer", IF(AND(R3085<10000000, S3085>50000000), "Overperformer", "Normal")) -> Normal | AA3085: =VLOOKUP(D3085, lookups!$A$2:$B$18, 2, FALSE) -> Medium Budget | AB3085: =IF(AND(N3085>7, T3085>1, U3085>70), "Recommended", "Not Recommended") -> Not Recommended | AC3085: =IF(N3085>=8, "High Buzz / High Score", IF(AND(N3085<6, T3085<1), "High Buzz Mismatch", "Normal")) -> Normal
... A3198: Gun Shy | B3198: 36884 | C3198: Color | D3198: Comedy | E3198: English | F3198: USA | G3198: R | H3198: Liam Neeson | I3198: Eric Blakeney | J3198: 14000 | K3198: 17665 | L3198: 3 | M3198: 242 | N3198: 5.7 | O3198: 49 | P3198: 101 | Q3198: 1631839 | R3198: 10000000 | S3198: =Q3198-R3198 -> -8368161 | T3198: =IF(R3198>0, (Q3198-R3198)/R3198, 0) -> -0.8368161 | U3198: =(N3198*4) + (T3198*0.4) + (M3198/10000) -> 22.489474 | V3198: =YEAR(B3198) -> 2000 | W3198: =TEXT(B3198, "mmmm") -> dekabr | X3198: =TRIM(I3198) -> Eric Blakeney | Y3198: =UPPER(A3198) -> GUN SHY | Z3198: =IF(AND(R3198>50000000, S3198<0), "Underperformer", IF(AND(R3198<10000000, S3198>50000000), "Overperformer", "Normal")) -> Normal | AA3198: =VLOOKUP(D3198, lookups!$A$2:$B$18, 2, FALSE) -> Medium Budget | AB3198: =IF(AND(N3198>7, T3198>1, U3198>70), "Recommended", "Not Recommended") -> Not Recommended | AC3198: =IF(N3198>=8, "High Buzz / High Score", IF(AND(N3198<6, T3198<1), "High Buzz Mismatch", "Normal")) -> High Buzz Mismatch
A3199: Kites | B3199: 40284 | C3199: Color | D3199: Action | E3199: English | F3199: India | H3199: BÃ¡rbara Mori | I3199: Anurag Basu | J3199: 594 | K3199: 1836 | L3199: 116 | M3199: 0 | N3199: 6 | O3199: 41 | P3199: 90 | Q3199: 1602466 | R3199: 600000000 | S3199: =Q3199-R3199 -> -598397534 | T3199: =IF(R3199>0, (Q3199-R3199)/R3199, 0) -> -0.99732922 | U3199: =(N3199*4) + (T3199*0.4) + (M3199/10000) -> 23.601068 | V3199: =YEAR(B3199) -> 2010 | W3199: =TEXT(B3199, "mmmm") -> aprel | X3199: =TRIM(I3199) -> Anurag Basu | Y3199: =UPPER(A3199) -> KİTES | Z3199: =IF(AND(R3199>50000000, S3199<0), "Underperformer", IF(AND(R3199<10000000, S3199>50000000), "Overperformer", "Normal")) -> Underperformer | AA3199: =VLOOKUP(D3199, lookups!$A$2:$B$18, 2, FALSE) -> High Budget | AB3199: =IF(AND(N3199>7, T3199>1, U3199>70), "Recommended", "Not Recommended") -> Not Recommended | AC3199: =IF(N3199>=8, "High Buzz / High Score", IF(AND(N3199<6, T3199<1), "High Buzz Mismatch", "Normal")) -> Normal
A3200: Your Sister's Sister | B3200: 40596 | C3200: Color | D3200: Comedy | E3200: English | F3200: USA | G3200: R | H3200: Mark Duplass | I3200: Lynn Shelton | J3200: 830 | K3200: 973 | L3200: 100 | M3200: 3000 | N3200: 6.7 | O3200: 171 | P3200: 90 | Q3200: 1573712 | R3200: 125000 | S3200: =Q3200-R3200 -> 1448712 | T3200: =IF(R3200>0, (Q3200-R3200)/R3200, 0) -> 11.589696 | U3200: =(N3200*4) + (T3200*0.4) + (M3200/10000) -> 31.735878 | V3200: =YEAR(B3200) -> 2011 | W3200: =TEXT(B3200, "mmmm") -> fevral | X3200: =TRIM(I3200) -> Lynn Shelton | Y3200: =UPPER(A3200) -> YOUR SİSTER'S SİSTER | Z3200: =IF(AND(R3200>50000000, S3200<0), "Underperformer", IF(AND(R3200<10000000, S3200>50000000), "Overperformer", "Normal")) -> Normal | AA3200: =VLOOKUP(D3200, lookups!$A$2:$B$18, 2, FALSE) -> Medium Budget | AB3200: =IF(AND(N3200>7, T3200>1, U3200>70), "Recommended", "Not Recommended") -> Not Recommended | AC3200: =IF(N3200>=8, "High Buzz / High Score", IF(AND(N3200<6, T3200<1), "High Buzz Mismatch", "Normal")) -> Normal
A3201: Veronica Guerin | B3201: 37847 | C3201: Color | D3201: Biography | E3201: English | F3201: Ireland | G3201: R | H3201: Brenda Fricker | I3201: Joel Schumacher | J3201: 214 | K3201: 409 | L3201: 541 | M3201: 0 | N3201: 6.9 | O3201: 106 | P3201: 98 | Q3201: 1569918 | R3201: 17000000 | S3201: =Q3201-R3201 -> -15430082 | T3201: =IF(R3201>0, (Q3201-R3201)/R3201, 0) -> -0.90765188 | U3201: =(N3201*4) + (T3201*0.4) + (M3201/10000) -> 27.236939 | V3201: =YEAR(B3201) -> 2003 | W3201: =TEXT(B3201, "mmmm") -> avgust | X3201: =TRIM(I3201) -> Joel Schumacher | Y3201: =UPPER(A3201) -> VERONİCA GUERİN | Z3201: =IF(AND(R3201>50000000, S3201<0), "Underperformer", IF(AND(R3201<10000000, S3201>50000000), "Overperformer", "Normal")) -> Normal | AA3201: =VLOOKUP(D3201, lookups!$A$2:$B$18, 2, FALSE) -> Medium Budget | AB3201: =IF(AND(N3201>7, T3201>1, U3201>70), "Recommended", "Not Recommended") -> Not Recommended | AC3201: =IF(N3201>=8, "High Buzz / High Score", IF(AND(N3201<6, T3201<1), "High Buzz Mismatch", "Normal")) -> Normal
A3202: BloodRayne | B3202: 38586 | C3202: Color | D3202: Action | E3202: English | F3202: USA | G3202: R | H3202: Meat Loaf | I3202: Uwe Boll | J3202: 783 | K3202: 2930 | L3202: 892 | M3202: 937 | N3202: 2.9 | O3202: 143 | P3202: 92 | Q3202: 1550000 | R3202: 25000000 | S3202: =Q3202-R3202 -> -23450000 | T3202: =IF(R3202>0, (Q3202-R3202)/R3202, 0) -> -0.938 | U3202: =(N3202*4) + (T3202*0.4) + (M3202/10000) -> 11.3185 | V3202: =YEAR(B3202) -> 2005 | W3202: =TEXT(B3202, "mmmm") -> avgust | X3202: =TRIM(I3202) -> Uwe Boll | Y3202: =UPPER(A3202) -> BLOODRAYNE | Z3202: =IF(AND(R3202>50000000, S3202<0), "Underperformer", IF(AND(R3202<10000000, S3202>50000000), "Overperformer", "Normal")) -> Normal | AA3202: =VLOOKUP(D3202, lookups!$A$2:$B$18, 2, FALSE) -> High Budget | AB3202: =IF(AND(N3202>7, T3202>1, U3202>70), "Recommended", "Not Recommended") -> Not Recommended | AC3202: =IF(N3202>=8, "High Buzz / High Score", IF(AND(N3202<6, T3202<1), "High Buzz Mismatch", "Normal")) -> High Buzz Mismatch
A3203: Trust the Man | B3203: 38534 | C3203: Color | D3203: Comedy | E3203: English | F3203: USA | G3203: R | H3203: Billy Crudup | I3203: Bart Freundlich | J3203: 745 | K3203: 1721 | L3203: 38 | M3203: 215 | N3203: 5.7 | O3203: 100 | P3203: 103 | Q3203: 1530535 | R3203: 9000000 | S3203: =Q3203-R3203 -> -7469465 | T3203: =IF(R3203>0, (Q3203-R3203)/R3203, 0) -> -0.82994056 | U3203: =(N3203*4) + (T3203*0.4) + (M3203/10000) -> 22.489524 | V3203: =YEAR(B3203) -> 2005 | W3203: =TEXT(B3203, "mmmm") -> iyul | X3203: =TRIM(I3203) -> Bart Freundlich | Y3203: =UPPER(A3203) -> TRUST THE MAN | Z3203: =IF(AND(R3203>50000000, S3203<0), "Underperformer", IF(AND(R3203<10000000, S3203>50000000), "Overperformer", "Normal")) -> Normal | AA3203: =VLOOKUP(D3203, lookups!$A$2:$B$18, 2, FALSE) -> Medium Budget | AB3203: =IF(AND(N3203>7, T3203>1, U3203>70), "Recommended", "Not Recommended") -> Not Recommended | AC3203: =IF(N3203>=8, "High Buzz / High Score", IF(AND(N3203<6, T3203<1), "High Buzz Mismatch", "Normal")) -> High Buzz Mismatch
A3204: Murderball | B3204: 38552 | C3204: Color | D3204: Documentary | E3204: English | F3204: USA | G3204: R | H3204: Mark Zupan | I3204: Henry Alex Rubin | J3204: 15 | K3204: 15 | L3204: 30 | M3204: 0 | N3204: 7.8 | O3204: 110 | P3204: 88 | Q3204: 1523883 | R3204: 1750211 | S3204: =Q3204-R3204 -> -226328 | T3204: =IF(R3204>0, (Q3204-R3204)/R3204, 0) -> -0.12931469 | U3204: =(N3204*4) + (T3204*0.4) + (M3204/10000) -> 31.148274 | V3204: =YEAR(B3204) -> 2005 | W3204: =TEXT(B3204, "mmmm") -> iyul | X3204: =TRIM(I3204) -> Henry Alex Rubin | Y3204: =UPPER(A3204) -> MURDERBALL | Z3204: =IF(AND(R3204>50000000, S3204<0), "Underperformer", IF(AND(R3204<10000000, S3204>50000000), "Overperformer", "Normal")) -> Normal | AA3204: =VLOOKUP(D3204, lookups!$A$2:$B$18, 2, FALSE) -> Low Budget | AB3204: =IF(AND(N3204>7, T3204>1, U3204>70), "Recommended", "Not Recommended") -> Not Recommended | AC3204: =IF(N3204>=8, "High Buzz / High Score", IF(AND(N3204<6, T3204<1), "High Buzz Mismatch", "Normal")) -> Normal
A3205: Oscar and Lucinda | B3205: 35479 | C3205: Color | D3205: Drama | E3205: English | F3205: USA | G3205: R | H3205: Tom Wilkinson | I3205: Gillian Armstrong | J3205: 1000 | K3205: 2004 | L3205: 44 | M3205: 329 | N3205: 6.7 | O3205: 28 | P3205: 132 | Q3205: 1508689 | R3205: 16000000 | S3205: =Q3205-R3205 -> -14491311 | T3205: =IF(R3205>0, (Q3205-R3205)/R3205, 0) -> -0.90570694 | U3205: =(N3205*4) + (T3205*0.4) + (M3205/10000) -> 26.470617 | V3205: =YEAR(B3205) -> 1997 | W3205: =TEXT(B3205, "mmmm") -> fevral | X3205: =TRIM(I3205) -> Gillian Armstrong | Y3205: =UPPER(A3205) -> OSCAR AND LUCİNDA | Z3205: =IF(AND(R3205>50000000, S3205<0), "Underperformer", IF(AND(R3205<10000000, S3205>50000000), "Overperformer", "Normal")) -> Normal | AA3205: =VLOOKUP(D3205, lookups!$A$2:$B$18, 2, FALSE) -> Medium Budget | AB3205: =IF(AND(N3205>7, T3205>1, U3205>70), "Recommended", "Not Recommended") -> Not Recommended | AC3205: =IF(N3205>=8, "High Buzz / High Score", IF(AND(N3205<6, T3205<1), "High Buzz Mismatch", "Normal")) -> Normal
A3206: Married Life | B3206: 39412 | C3206: Color | D3206: Crime | E3206: English | F3206: USA | G3206: PG-13 | H3206: David Richmond-Peck | I3206: Ira Sachs | J3206: 60 | K3206: 141 | L3206: 60 | M3206: 314 | N3206: 6.3 | O3206: 121 | P3206: 91 | Q3206: 1506998 | R3206: 12000000 | S3206: =Q3206-R3206 -> -10493002 | T3206: =IF(R3206>0, (Q3206-R3206)/R3206, 0) -> -0.87441683 | U3206: =(N3206*4) + (T3206*0.4) + (M3206/10000) -> 24.881633 | V3206: =YEAR(B3206) -> 2007 | W3206: =TEXT(B3206, "mmmm") -> noyabr | X3206: =TRIM(I3206) -> Ira Sachs | Y3206: =UPPER(A3206) -> MARRİED LİFE | Z3206: =IF(AND(R3206>50000000, S3206<0), "Underperformer", IF(AND(R3206<10000000, S3206>50000000), "Overperformer", "Normal")) -> Normal | AA3206: =VLOOKUP(D3206, lookups!$A$2:$B$18, 2, FALSE) -> Medium Budget | AB3206: =IF(AND(N3206>7, T3206>1, U3206>70), "Recommended", "Not Recommended") -> Not Recommended | AC3206: =IF(N3206>=8, "High Buzz / High Score", IF(AND(N3206<6, T3206<1), "High Buzz Mismatch", "Normal")) -> Normal
A3207: Heaven's Gate | B3207: 29261 | C3207: Color | D3207: Adventure | E3207: English | F3207: USA | G3207: R | H3207: Jeff Bridges | I3207: Michael Cimino | J3207: 12000 | K3207: 14255 | L3207: 517 | M3207: 1000 | N3207: 6.8 | O3207: 102 | P3207: 325 | Q3207: 1500000 | R3207: 44000000 | S3207: =Q3207-R3207 -> -42500000 | T3207: =IF(R3207>0, (Q3207-R3207)/R3207, 0) -> -0.96590909 | U3207: =(N3207*4) + (T3207*0.4) + (M3207/10000) -> 26.913636 | V3207: =YEAR(B3207) -> 1980 | W3207: =TEXT(B3207, "mmmm") -> fevral | X3207: =TRIM(I3207) -> Michael Cimino | Y3207: =UPPER(A3207) -> HEAVEN'S GATE | Z3207: =IF(AND(R3207>50000000, S3207<0), "Underperformer", IF(AND(R3207<10000000, S3207>50000000), "Overperformer", "Normal")) -> Normal | AA3207: =VLOOKUP(D3207, lookups!$A$2:$B$18, 2, FALSE) -> High Budget | AB3207: =IF(AND(N3207>7, T3207>1, U3207>70), "Recommended", "Not Recommended") -> Not Recommended | AC3207: =IF(N3207>=8, "High Buzz / High Score", IF(AND(N3207<6, T3207<1), "High Buzz Mismatch", "Normal")) -> Normal
A3208: Night Watch | B3208: 38085 | C3208: Color | D3208: Fantasy | E3208: Russian | F3208: Russia | G3208: R | H3208: Konstantin Khabenskiy | I3208: Timur Bekmambetov | J3208: 114 | K3208: 206 | L3208: 335 | M3208: 0 | N3208: 6.5 | O3208: 232 | P3208: 104 | Q3208: 1487477 | R3208: 4200000 | S3208: =Q3208-R3208 -> -2712523 | T3208: =IF(R3208>0, (Q3208-R3208)/R3208, 0) -> -0.64583881 | U3208: =(N3208*4) + (T3208*0.4) + (M3208/10000) -> 25.741664 | V3208: =YEAR(B3208) -> 2004 | W3208: =TEXT(B3208, "mmmm") -> aprel | X3208: =TRIM(I3208) -> Timur Bekmambetov | Y3208: =UPPER(A3208) -> NİGHT WATCH | Z3208: =IF(AND(R3208>50000000, S3208<0), "Underperformer", IF(AND(R3208<10000000, S3208>50000000), "Overperformer", "Normal")) -> Normal | AA3208: =VLOOKUP(D3208, lookups!$A$2:$B$18, 2, FALSE) -> Low Budget | AB3208: =IF(AND(N3208>7, T3208>1, U3208>70), "Recommended", "Not Recommended") -> Not Recommended | AC3208: =IF(N3208>=8, "High Buzz / High Score", IF(AND(N3208<6, T3208<1), "High Buzz Mismatch", "Normal")) -> Normal
A3209: The Diary of a Teenage Girl | B3209: 42011 | C3209: Color | D3209: Drama | E3209: English | F3209: USA | G3209: R | H3209: Alexander SkarsgÃ¥rd | I3209: Marielle Heller | J3209: 10000 | K3209: 11184 | L3209: 22 | M3209: 0 | N3209: 6.9 | O3209: 168 | P3209: 102 | Q3209: 1477002 | R3209: 2000000 | S3209: =Q3209-R3209 -> -522998 | T3209: =IF(R3209>0, (Q3209-R3209)/R3209, 0) -> -0.261499 | U3209: =(N3209*4) + (T3209*0.4) + (M3209/10000) -> 27.4954 | V3209: =YEAR(B3209) -> 2015 | W3209: =TEXT(B3209, "mmmm") -> yanvar | X3209: =TRIM(I3209) -> Marielle Heller | Y3209: =UPPER(A3209) -> THE DİARY OF A TEENAGE GİRL | Z3209: =IF(AND(R3209>50000000, S3209<0), "Underperformer", IF(AND(R3209<10000000, S3209>50000000), "Overperformer", "Normal")) -> Normal | AA3209: =VLOOKUP(D3209, lookups!$A$2:$B$18, 2, FALSE) -> Medium Budget | AB3209: =IF(AND(N3209>7, T3209>1, U3209>70), "Recommended", "Not Recommended") -> Not Recommended | AC3209: =IF(N3209>=8, "High Buzz / High Score", IF(AND(N3209<6, T3209<1), "High Buzz Mismatch", "Normal")) -> Normal
A3210: The Joneses | B3210: 40142 | C3210: Color | D3210: Comedy | E3210: English | F3210: USA | G3210: R | H3210: Demi Moore | I3210: Derrick Borte | J3210: 2000 | K3210: 4607 | L3210: 17 | M3210: 0 | N3210: 6.5 | O3210: 144 | P3210: 96 | Q3210: 1474508 | R3210: 5000000 | S3210: =Q3210-R3210 -> -3525492 | T3210: =IF(R3210>0, (Q3210-R3210)/R3210, 0) -> -0.7050984 | U3210: =(N3210*4) + (T3210*0.4) + (M3210/10000) -> 25.717961 | V3210: =YEAR(B3210) -> 2009 | W3210: =TEXT(B3210, "mmmm") -> noyabr | X3210: =TRIM(I3210) -> Derrick Borte | Y3210: =UPPER(A3210) -> THE JONESES | Z3210: =IF(AND(R3210>50000000, S3210<0), "Underperformer", IF(AND(R3210<10000000, S3210>50000000), "Overperformer", "Normal")) -> Normal | AA3210: =VLOOKUP(D3210, lookups!$A$2:$B$18, 2, FALSE) -> Medium Budget | AB3210: =IF(AND(N3210>7, T3210>1, U3210>70), "Recommended", "Not Recommended") -> Not Recommended | AC3210: =IF(N3210>=8, "High Buzz / High Score", IF(AND(N3210<6, T3210<1), "High Buzz Mismatch", "Normal")) -> Normal
A3211: No End in Sight | B3211: 39248 | C3211: Color | D3211: Documentary | E3211: English | F3211: USA | H3211: Campbell Scott | I3211: Charles Ferguson | J3211: 393 | K3211: 446 | L3211: 117 | M3211: 0 | N3211: 8.3 | O3211: 79 | P3211: 102 | Q3211: 1430185 | R3211: 2000000 | S3211: =Q3211-R3211 -> -569815 | T3211: =IF(R3211>0, (Q3211-R3211)/R3211, 0) -> -0.2849075 | U3211: =(N3211*4) + (T3211*0.4) + (M3211/10000) -> 33.086037 | V3211: =YEAR(B3211) -> 2007 | W3211: =TEXT(B3211, "mmmm") -> iyun | X3211: =TRIM(I3211) -> Charles Ferguson | Y3211: =UPPER(A3211) -> NO END İN SİGHT | Z3211: =IF(AND(R3211>50000000, S3211<0), "Underperformer", IF(AND(R3211<10000000, S3211>50000000), "Overperformer", "Normal")) -> Normal | AA3211: =VLOOKUP(D3211, lookups!$A$2:$B$18, 2, FALSE) -> Low Budget | AB3211: =IF(AND(N3211>7, T3211>1, U3211>70), "Recommended", "Not Recommended") -> Not Recommended | AC3211: =IF(N3211>=8, "High Buzz / High Score", IF(AND(N3211<6, T3211<1), "High Buzz Mismatch", "Normal")) -> High Buzz / High Score
...

Sheet lookups
A1: Genre | B1: Genre Category
A2: Action | B2: High Budget
A3: Adventure | B3: High Budget
A4: Animation | B4: High Budget
A5: Biography | B5: Medium Budget
A6: Comedy | B6: Medium Budget
A7: Crime | B7: Medium Budget
A8: Documentary | B8: Low Budget
A9: Drama | B9: Medium Budget
A10: Family | B10: Low Budget
A11: Fantasy | B11: Low Budget
A12: Horror | B12: Low Budget
... A18: Western | B18: Low Budget

Sheet pivot_tables
A1: Row Labels | B1: Average of IMDb Score (1-10) | C1: Average of Success Score | E1: Row Labels | F1: Count of Title | M1: Row Labels | N1: Average of IMDb Score (1-10) | O1: Average of Gross Revenue | P1: Average of Duration (min) | R1: Sum of Gross Revenue | S1: Sum of Profit | T1: Average of IMDb Score (1-10) | U1: Count of Movie Title(UPPER)
A2: Horror | B2: 5.7915584 | C2: 52.240882 | E2: Christopher Nolan | F2: 8 | M2: Black and White | N2: 7.1085938 | O2: 32888710 | P2: 115.55469 | R2: 185670019307 | S2: 19978735058 | T2: 6.4628143 | U2: 3738
A3: Biography | B3: 7.1502439 | C3: 35.476621 | E3: Quentin Tarantino | F3: 8 | M3: Color | N3: 6.4399169 | O3: 50266001 | P3: 109.55112
A4: Musical | B4: 6.75 | C4: 34.785478 | E4: Hayao Miyazaki | F4: 4 | M4: Grand Total | N4: 6.4628143 | O4: 49670952 | P4: 109.75676
A5: Family | B5: 6.5 | C5: 32.405196 | E5: Grand Total | F5: 20
A6: Western | B6: 6.7666667 | C6: 29.894958 | I6: Row Labels | J6: Sum of Budget | K6: Sum of Gross Revenue | L6: Average of Budget | R6: Row Labels | S6: Max of ROI(%)
A7: Documentary | B7: 6.9522727 | C7: 29.7862 | E7: Row Labels | F7: Count of Title | G7: Average of IMDb Score (1-10) | I7: Australia | J7: 1343505523 | K7: 1506979847 | L7: 34448860 | R7: Paranormal Activity | S7: 7193.4855
A8: Animation | B8: 6.7622222 | C8: 29.137409 | E8: Christopher Nolan | F8: 8 | G8: 8.4125 | I8: Canada | J8: 1364990000 | K8: 1575353290 | L8: 21666508 | R8: Tarnation | S8: 2714.6606
A9: Crime | B9: 6.9376984 | C9: 28.98995 | E9: Hayao Miyazaki | F9: 4 | G9: 8.225 | I9: France | J9: 3613494500 | K9: 1885953657 | L9: 34414233 | R9: The Blair Witch Project | S9: 2341.1686
A10: Drama | B10: 6.8238872 | C10: 28.944132 | E10: Quentin Tarantino | F10: 8 | G10: 8.2 | I10: Germany | J10: 2853400000 | K10: 2291916683 | L10: 36118987 | R10: The Brothers McMullen | S10: 408.864
A11: Adventure | B11: 6.5568681 | C11: 28.068889 | E11: Milos Forman | F11: 3 | G11: 8.1333333 | I11: Hungary | J11: 2520000000 | K11: 23375191 | L11: 1260000000 | R11: The Texas Chain Saw Massacre | S11: 368.42729
A12: Mystery | B12: 6.5869565 | C12: 27.964705 | E12: Pete Docter | F12: 3 | G12: 8.2333333 | I12: India | J12: 1576543748 | K12: 40578143 | L12: 1.1261027e+08 | R12: El Mariachi | S12: 290.56
A13: Fantasy | B13: 6.2342857 | C13: 27.949145 | E13: Sergio Leone | F13: 3 | G13: 8.4333333 | I13: Japan | J13: 6913919898 | K13: 356915645 | L13: 4.0670117e+08 | R13: The Gallows | S13: 226.57819
A14: Sci-Fi | B14: 6.5875 | C14: 27.194027 | E14: Grand Total | F14: 29 | G14: 8.2827586 | I14: South Korea | J14: 16528900000 | K14: 21516040 | L14: 2066112500 | R14: Super Size Me | S14: 176.37489
A15: Action | B15: 6.2802661 | C15: 26.527607 | I15: UK | J15: 8616094127 | K15: 9842363547 | L15: 28157170 | R15: Halloween | S15: 155.66667
A16: Romance | B16: 6.1333333 | C16: 26.189509 | E16: Row Labels | F16: Average of Gross Revenue | G16: Sum of Cast FB Likes | I16: USA | J16: 114973672678 | K16: 165884530622 | L16: 38934532 | R16: American Graffiti | S16: 147.00515
A17: Comedy | B17: 6.1699411 | C17: 26.0894 | E17: Anchorman: The Legend of Ron Burgundy | F17: 84136909 | G17: 656730 | I17: Grand Total | J17: 160304520474 | K17: 183429482665 | L17: 44702878 | R17: Grand Total | S17: 7193.4855
A18: Thriller | B18: 5.3 | C18: 22.152338 | E18: Armored | F18: 15988876 | G18: 137712
A19: Grand Total | B19: 6.4628143 | C19: 28.81162 | E19: Evan Almighty | F19: 100289690 | G19: 108016
E20: Firewall | F20: 48745150 | G20: 101383
A21: Horror , Biography və Musical janrları ən yüksək orta Success Score-a malikdir | E21: Hardflip | F21: 96734 | G21: 263584
E22: Hostage | F22: 34636443 | G22: 103354
E23: Quarantine | F23: 31691811 | G23: 140268
E24: The Amityville Horror | F24: 64255243 | G24: 120797
E25: The Dark Knight Rises | F25: 448130642 | G25: 106759
E26: The Final Destination | F26: 66466372 | G26: 303717
E27: Grand Total | F27: 89443787 | G27: 2042320
E44: Row Labels | F44: Sum of Movie FB Likes | G44: Average of IMDb Score (1-10) | H44: Sum of Gross Revenue
E45: THE REVENANT | F45: 190000 | G45: 8.1 | H45: 183635922
E46: THE MARTİAN | F46: 153000 | G46: 8.1 | H46: 228430993
E47: THE IMİTATİON GAME | F47: 165000 | G47: 8.1 | H47: 91121452
E48: THE HOBBİT: AN UNEXPECTED JOURNEY | F48: 166000 | G48: 7.9 | H48: 303001229
E49: THE DARK KNİGHT RİSES | F49: 164000 | G49: 8.4 | H49: 448130642
E50: MAD MAX: FURY ROAD | F50: 191000 | G50: 8.1 | H50: 153629485
E51: JURASSİC WORLD | F51: 150000 | G51: 7 | H51: 652177271
E52: INTERSTELLAR | F52: 349000 | G52: 8.6 | H52: 187991439
E53: INCEPTİON | F53: 175000 | G53: 8.8 | H53: 292568851
E54: DJANGO UNCHAİNED | F54: 199000 | G54: 8.5 | H54: 162804648
E55: Grand Total | F55: 1902000 | G55: 8.16 | H55: 2703491932

Sheet dashboard
A1: "IMDB Movies & Directors Analytics Dashboard"
B2: Total Revenue | E2: Total Profit | H2: Average IMDb Score | K2: Total Movies
B3: =GETPIVOTDATA("Sum of Gross Revenue",pivot_tables!$R$1) -> 185670019307 | E3: =GETPIVOTDATA("Sum of Profit",pivot_tables!$R$1) -> 19978735058 | H3: =GETPIVOTDATA("Average of IMDb Score (1-10)",pivot_tables!$R$1) -> 6.4628143 | K3: =GETPIVOTDATA("Count of Movie Title(UPPER)",pivot_tables!$R$1) -> 3738
